{"hands_on_practices": [{"introduction": "掌握函数在一点连续的 $\\epsilon-\\delta$ 定义是实分析的基础。这个练习将带你实践如何为一个给定的多项式函数，通过严格的 $\\epsilon-\\delta$ 论证来证明其在任意点的连续性。通过构建关键的不等式并找到依赖于点 $c$ 和 $\\epsilon$ 的 $\\delta$ [@problem_id:1291663]，你将学会处理这类证明的核心技巧，从而将抽象的定义转化为具体的解题步骤。", "problem": "连续性的 $\\epsilon$-$\\delta$ 判据指出，一个函数 $f(x)$ 在点 $x=c$ 处连续，是指对于任意 $\\epsilon > 0$，存在一个 $\\delta > 0$，使得对于所有满足 $|x-c|  \\delta$ 的 $x$，都有 $|f(x)-f(c)|  \\epsilon$。\n\n考虑函数 $f(x) = x^3 - 5x + 6$。在证明其在任意点 $c$ 处的连续性时，一个常见的策略是首先用一个初始界限（如 $\\delta \\leq 1$）来限制 $\\delta$。这个预备步骤简化了为表达式 $|f(x)-f(c)|$ 中较复杂部分寻找上界的过程。\n\n对于一个给定的点 $c$，遵循此策略，$\\delta$ 的一个有效选择可以表示为 $\\delta = \\min\\left(1, \\frac{\\epsilon}{K}\\right)$ 的形式，其中 $K$ 是一个依赖于点 $c$ 的表达式。\n\n确定 $K$ 的表达式，该表达式需确保对于任意 $\\epsilon > 0$，此 $\\delta$ 的选择都有效，并且在给定约束下使 $\\delta$ 尽可能大。", "solution": "我们从函数 $f(x) = x^{3} - 5x + 6$ 开始，并固定一个任意的 $c \\in \\mathbb{R}$。对任意 $x$，计算\n$$\nf(x) - f(c) = (x^{3} - c^{3}) - 5(x - c) = (x - c)(x^{2} + xc + c^{2} - 5).\n$$\n取绝对值得\n$$\n|f(x) - f(c)| = |x - c|\\,|x^{2} + xc + c^{2} - 5|.\n$$\n为了控制因子 $|x^{2} + xc + c^{2} - 5|$，我们采用预备限制 $\\delta \\leq 1$。因此，只要 $|x - c|  \\delta \\leq 1$，我们就有 $|x| \\leq |c| + 1$。利用三角不等式和基本界限，我们得到\n$$\n|x^{2} + xc + c^{2} - 5| \\leq |x|^{2} + |x||c| + c^{2} + 5 \\leq (|c| + 1)^{2} + (|c| + 1)|c| + c^{2} + 5.\n$$\n因为 $|c|^{2} = c^{2}$，上式可简化为\n$$\n(|c| + 1)^{2} + (|c| + 1)|c| + c^{2} + 5\n= (|c|^{2} + 2|c| + 1) + (|c|^{2} + |c|) + c^{2} + 5\n= 3c^{2} + 3|c| + 6.\n$$\n因此，\n$$\n|f(x) - f(c)| \\leq \\bigl(3c^{2} + 3|c| + 6\\bigr)\\,|x - c|.\n$$\n于是，如果我们选择\n$$\n\\delta = \\min\\left(1,\\ \\frac{\\epsilon}{K}\\right) \\quad \\text{其中} \\quad K = 3c^{2} + 3|c| + 6,\n$$\n那么对于任意 $\\epsilon > 0$ 和任意满足 $|x - c|  \\delta$ 的 $x$，我们同时有 $|x - c|  1$ 和\n$$\n|f(x) - f(c)| \\leq K\\,|x - c|  K \\cdot \\frac{\\epsilon}{K} = \\epsilon.\n$$\n这就确立了在 $c$ 点的连续性的 $\\epsilon$-$\\delta$ 条件。在 $|x - c|  1$ 的约束下，通过标准的三角不等式估计和关系式 $|x| \\leq |c| + 1$ 所得到的界中，表达式 $K = 3c^{2} + 3|c| + 6$ 是最小的，因此它在给定约束下使 $\\delta$ 尽可能大。", "answer": "$$\\boxed{3c^{2} + 3|c| + 6}$$", "id": "1291663"}, {"introduction": "除了 $\\epsilon-\\delta$ 定义，序列判据为我们提供了判断函数极限存在性与连续性的另一个强大工具。这个方法在证明函数不连续时尤其有效，因为它只需要找到两个趋向同一点但函数值趋向不同极限的序列即可。本题 [@problem_id:1291627] 中的函数在 $x=0$ 附近剧烈振荡，是展示如何运用序列判据证明不连续性的经典例子，有助于你更直观地理解极限不存在的情形。", "problem": "考虑由法则 $f(x) = A \\cos(\\frac{\\pi}{x}) + B$ 定义的函数 $f: \\mathbb{R}\\setminus\\{0\\} \\to \\mathbb{R}$，其中 $A$ 和 $B$ 是实常数且 $A \\neq 0$。\n\n根据极限的序列判据，当 $x$ 趋近于 $c$ 时 $f(x)$ 的极限存在，当且仅当对于每个收敛到 $c$ 的序列 $(x_n)$，序列 $(f(x_n))$ 都收敛到相同的值。对于给定的函数 $f(x)$，当 $x$ 趋近于 $0$ 时，此判据不成立。具体来说，可以找到两个不同的序列，记作 $(x_n)_{n=1}^\\infty$ 和 $(y_n)_{n=1}^\\infty$，它们都收敛到 $0$，但其对应的函数值序列的极限 $L_1 = \\lim_{n\\to\\infty} f(x_n)$ 和 $L_2 = \\lim_{n\\to\\infty} f(y_n)$ 存在且不相同。\n\n请用常数 $A$ 和 $B$ 来表示这两个不同的极限值 $L_1$ 和 $L_2$。", "solution": "我们使用极限的序列判据来找出两个收敛到零的序列，它们在 $x \\to 0$ 时会得到 $f(x)=A\\cos\\!\\left(\\frac{\\pi}{x}\\right)+B$ 的不同极限值。\n\n对于 $n \\in \\mathbb{N}$，定义序列 $x_{n}=\\frac{1}{2n}$ 和 $y_{n}=\\frac{1}{2n+1}$。它们都满足\n$$\n\\lim_{n \\to \\infty} x_{n}=\\lim_{n \\to \\infty} \\frac{1}{2n}=0, \\qquad \\lim_{n \\to \\infty} y_{n}=\\lim_{n \\to \\infty} \\frac{1}{2n+1}=0,\n$$\n所以 $x_{n} \\to 0$ 且 $y_{n} \\to 0$。\n\n沿着这些序列计算函数值。对于 $x_{n}$，\n$$\n\\frac{\\pi}{x_{n}}=\\pi \\cdot 2n=2n\\pi \\quad \\Rightarrow \\quad \\cos\\!\\left(\\frac{\\pi}{x_{n}}\\right)=\\cos(2n\\pi)=1,\n$$\n因此\n$$\nf(x_{n})=A\\cdot 1 + B = A+B,\n$$\n所以\n$$\n\\lim_{n \\to \\infty} f(x_{n})=A+B.\n$$\n\n对于 $y_{n}$，\n$$\n\\frac{\\pi}{y_{n}}=\\pi \\cdot (2n+1)=(2n+1)\\pi \\quad \\Rightarrow \\quad \\cos\\!\\left(\\frac{\\pi}{y_{n}}\\right)=\\cos\\!\\big((2n+1)\\pi\\big)=-1,\n$$\n因此\n$$\nf(y_{n})=A\\cdot(-1)+B = B-A,\n$$\n所以\n$$\n\\lim_{n \\to \\infty} f(y_{n})=B-A.\n$$\n\n因为 $A \\neq 0$，所以这些极限是不同的，因为\n$$\n(A+B)-(B-A)=2A \\neq 0.\n$$\n因此，通过趋近于 $0$ 的序列得到的两个不同极限值为 $A+B$ 和 $B-A$。", "answer": "$$\\boxed{A+B, B-A}$$", "id": "1291627"}, {"introduction": "连续性的概念在面对一些“奇异”函数时会变得格外有趣和深刻。本题 [@problem_id:1291650] 提出的函数在有理数和无理数上取不同的表达式，迫使我们思考在实数稠密性的背景下，极限如何形成。通过分析在何处两种表达式的值会相等，你将发现即使是这样一个“行为分裂”的函数，也可能在特定的点上保持连续，这极大地加深了对连续性局部性质的理解。", "problem": "考虑一个函数 $f: \\mathbb{R} \\to \\mathbb{R}$，其定义取决于其输入的有理性。对于任何有理数 $x$（可以表示为两个整数之分数的数），函数的值由 $f(x) = x$ 给出。对于任何无理数 $x$，函数的值由 $f(x) = x^2$ 给出。\n\n下列哪个陈述准确地描述了函数 $f$ 连续的点集？\n\nA. 该函数处处不连续。\n\nB. 该函数仅在点 $x=0$ 处连续。\n\nC. 该函数仅在点 $x=1$ 处连续。\n\nD. 该函数仅在点 $x=0$ 和 $x=1$ 处连续。\n\nE. 该函数对所有有理数连续，但对所有无理数不连续。\n\nF. 该函数对所有无理数连续，但对所有有理数不连续。\n\nG. 该函数对所有实数 $x \\in \\mathbb{R}$ 连续。", "solution": "要确定函数 $f(x)$ 在何处连续，我们必须找出那些点 $c$，在这些点上当 $x$ 趋近于 $c$ 时 $f(x)$ 的极限存在且等于 $f(c)$。即 $\\lim_{x\\to c} f(x) = f(c)$。\n\n实数的一个关键性质是，有理数集 $\\mathbb{Q}$ 和无理数集 $\\mathbb{R}\\setminus\\mathbb{Q}$ 都在 $\\mathbb{R}$ 中是稠密的。这意味着围绕任何实数 $c$ 的任何区间都包含有理数和无理数。因此，为了使极限 $\\lim_{x\\to c} f(x)$ 存在，$f(x)$ 所趋近的值必须相同，无论 $x$ 是通过有理数序列还是无理数序列趋近于 $c$。\n\n我们来考虑一个任意点 $c \\in \\mathbb{R}$。\n设 $(q_n)$ 是一个有理数序列，使得当 $n \\to \\infty$ 时 $q_n \\to c$。根据 $f$ 的定义，我们有 $f(q_n) = q_n$。因此，$\\lim_{n \\to \\infty} f(q_n) = \\lim_{n \\to \\infty} q_n = c$。\n设 $(i_n)$ 是一个无理数序列，使得当 $n \\to \\infty$ 时 $i_n \\to c$。根据 $f$ 的定义，我们有 $f(i_n) = i_n^2$。因此，$\\lim_{n \\to \\infty} f(i_n) = \\lim_{n \\to \\infty} i_n^2 = c^2$。\n\n为了使极限 $\\lim_{x\\to c} f(x)$ 存在，这两个极限必须相等：\n$$c = c^2$$\n这个方程给出了我们可能的连续点。我们可以解出 $c$：\n$$c^2 - c = 0$$\n$$c(c-1) = 0$$\n解是 $c=0$ 和 $c=1$。因此，该函数只能在 $x=0$ 和 $x=1$ 处连续。我们现在必须正式检查它是否确实在这两个点上连续。\n\n**情况 1：在 $c=0$ 处检验连续性。**\n因为 $0$ 是一个有理数，所以 $f(0)=0$。\n根据我们上面的分析，当我们通过有理数趋近于 $0$ 时，极限是 $0$；当我们通过无理数趋近于 $0$ 时，极限是 $0^2=0$。由于两个极限一致，所以 $\\lim_{x\\to 0} f(x) = 0$。\n因为 $\\lim_{x\\to 0} f(x) = 0 = f(0)$，所以函数在 $x=0$ 处是连续的。\n\n**情况 2：在 $c=1$ 处检验连续性。**\n因为 $1$ 是一个有理数，所以 $f(1)=1$。\n根据我们上面的分析，当我们通过有理数趋近于 $1$ 时，极限是 $1$；当我们通过无理数趋近于 $1$ 时，极限是 $1^2=1$。由于两个极限一致，所以 $\\lim_{x\\to 1} f(x) = 1$。\n因为 $\\lim_{x\\to 1} f(x) = 1 = f(1)$，所以函数在 $x=1$ 处是连续的。\n\n**情况 3：在任何其他点 $c \\notin \\{0, 1\\}$ 处检验连续性。**\n如果 $c$ 是除 $0$ 或 $1$ 之外的任何实数，则 $c \\neq c^2$。\n正如我们所展示的，如果我们通过一个有理数序列趋近于 $c$，函数值趋近于 $c$。如果我们通过一个无理数序列趋近于 $c$，函数值趋近于 $c^2$。由于 $c \\neq c^2$，极限 $\\lim_{x\\to c} f(x)$ 不存在。一个函数在极限不存在的点上不可能是连续的。\n因此，除了 $x=0$ 和 $x=1$，$f(x)$ 在所有点 $x \\in \\mathbb{R}$ 处都是不连续的。\n\n基于此分析，函数 $f$ 仅在点 $x=0$ 和 $x=1$ 处连续。这对应于选项 D。", "answer": "$$\\boxed{D}$$", "id": "1291650"}]}