{"hands_on_practices": [{"introduction": "Read-Newns 路径积分方法的核心在于求解一组鞍点方程，以确定系统的低能有效参数。此练习将引导您完成一个基础但至关重要的计算：在近藤区（Kondo regime）求解鞍点方程，以推导近藤温度 $T_K$。通过这个过程，您将亲身体会非微扰的能量尺度如何从模型的微观参数中涌现出来 [@problem_id:1189231]。", "problem": "在 Read-Newns 从属玻色子路径积分方法处理大 $N$ 极限下的 Anderson 杂质模型中，Kondo 区域（$U \\to \\infty$）中系统的性质可以由一组鞍点方程确定。在零温下，代表系统特征能标的 Kondo 温度 $T_K$ 可以被认为是杂质的重整化能级 $\\tilde{\\epsilon}_d$。该重整化能级由以下鞍点方程确定：\n\n$$\n\\tilde{\\epsilon}_d - \\epsilon_d = \\frac{1}{\\pi} \\int_{-D}^{0} d\\omega \\, \\frac{\\Gamma(\\omega)}{\\omega - \\tilde{\\epsilon}_d}\n$$\n\n这里，$\\epsilon_d$ 是杂质能级的裸能量，$D$ 是导带的半带宽，费米能级设置在零能量处。函数 $\\Gamma(\\omega)$ 是杂化函数，它描述了杂质与导带电子之间的耦合。\n\n考虑一个具有如下半椭圆杂化函数的系统：\n$$\n\\Gamma(\\omega) = \\frac{\\Gamma_0}{D} \\sqrt{D^2 - \\omega^2}, \\quad \\text{对于 } |\\omega| \\le D\n$$\n其他情况下 $\\Gamma(\\omega)=0$。$\\Gamma_0$ 是费米能级处的杂化强度。\n\n假设系统处于深度 Kondo 区域，这意味着 $|\\epsilon_d| \\gg \\Gamma_0$ 且 $D \\gg \\Gamma_0$。因此，Kondo 温度非常小，$T_K = \\tilde{\\epsilon}_d \\ll D$。你的任务是求解鞍点方程，以找出 Kondo 温度 $T_K$ 关于 $D$、$\\Gamma_0$ 和 $\\epsilon_d$ 的显式表达式。", "solution": "我们从零温鞍点方程开始\n$$\n\\tilde\\epsilon_d-\\epsilon_d\n=\\frac1\\pi\\int_{-D}^{0}d\\omega\\;\\frac{\\Gamma(\\omega)}{\\omega-\\tilde\\epsilon_d},\n$$\n其中半椭圆杂化函数为\n$$\n\\Gamma(\\omega)=\\frac{\\Gamma_0}{D}\\sqrt{D^2-\\omega^2},\\quad|\\omega|\\le D.\n$$\n定义积分\n$$\nI\\equiv\\int_{-D}^0d\\omega\\,\\frac{\\sqrt{D^2-\\omega^2}}{\\omega-\\tilde\\epsilon_d},\n$$\n这样\n$$\n\\tilde\\epsilon_d-\\epsilon_d\n=\\frac{\\Gamma_0}{\\pi D}\\,I.\n$$\n换元 $x=-\\omega$，其中 $x\\in[0,D]$，\n$$\nI=\\int_0^Ddx\\;\\frac{\\sqrt{D^2-x^2}}{x+\\tilde\\epsilon_d}.\n$$\n接下来令 $x=D\\sin\\theta$，其中 $\\theta\\in[0,\\pi/2]$，这样\n$$\nI\n=\\int_0^{\\pi/2}D\\cos\\theta\\,\n\\frac{D\\cos\\theta\\,d\\theta}{D\\sin\\theta+\\tilde\\epsilon_d}\n=D\\int_0^{\\pi/2}\\frac{\\cos^2\\theta\\,d\\theta}{\\sin\\theta+a},\n\\quad a\\equiv\\frac{\\tilde\\epsilon_d}{D}\\ll1.\n$$\n将 $\\cos^2\\theta=1-\\sin^2\\theta$ 写入并分解积分。对于 $a\\ll1$，可以发现\n$$\nI\\approx D\\Bigl[\\int_0^{\\pi/2}\\frac{d\\theta}{\\sin\\theta+a}-1\\Bigr]\n\\approx D\\bigl[\\ln\\!\\tfrac{2}{a}-1\\bigr]\n=D\\bigl[\\ln\\tfrac{2D}{\\tilde\\epsilon_d}-1\\bigr].\n$$\n因此鞍点方程变为\n$$\n\\tilde\\epsilon_d-\\epsilon_d\n=\\frac{\\Gamma_0}{\\pi}\\Bigl[\\ln\\frac{2D}{\\tilde\\epsilon_d}-1\\Bigr].\n$$\n在深度 Kondo 区域 $|\\epsilon_d|\\gg\\Gamma_0$ 中，求解此超越方程时，注意到 $\\tilde\\epsilon_d\\ll|\\epsilon_d|$，故左侧的 $\\tilde\\epsilon_d$ 项可以忽略。于是大项 $-\\epsilon_d$ 与右侧的对数项相平衡，我们得到\n$$\n\\tilde\\epsilon_d\n\\approx\\frac{2D}{e}\\,\\exp\\!\\Bigl(-\\frac{\\pi|\\epsilon_d|}{\\Gamma_0}\\Bigr).\n$$\n将 $T_K=\\tilde\\epsilon_d$ 等同起来，便得到最终结果。", "answer": "$$\n\\boxed{\\frac{2D}{e}\\,\\exp\\!\\Bigl(-\\frac{\\pi|\\epsilon_d|}{\\Gamma_0}\\Bigr)}\n$$", "id": "1189231"}, {"introduction": "鞍点近似不仅给出了系统的基态能量，还揭示了杂质对系统态密度的贡献，通常表现为一个洛伦兹型的共振峰。这个练习旨在将这一理论结果与一个可测量的宏观物理量联系起来，即低温下的电子比热。通过应用 Sommerfeld 展开，您将计算出线性比热系数 $\\gamma$，这直接反映了近藤共振在费米能级处贡献的态密度，也是理解重费米子行为的关键一步 [@problem_id:1189270]。", "problem": "Read-Newns 从属玻色子路径积分形式是研究强关联杂质系统（如安德森杂质模型）的一种强大的非微扰方法。在这种方法中，物理电子算符由一个从属玻色子算符和一个赝费米子算符的乘积表示，并受到一个防止非物理态出现的约束。对于具有大在位库仑排斥 $U$ 的杂质，路径积分中的鞍点近似（等效于大 N 展开，其中 N 是自旋-轨道简并度）导出了一个由共振能级散射的无相互作用赝费米子的有效低能理论。\n\n从该鞍点解导出的杂质对系统态密度的贡献 $\\Delta\\rho(\\omega)$，呈现为一个中心在有效能量 $\\epsilon^*$、宽度为 $\\Delta^*$ 的洛伦兹形式：\n$$\n\\Delta\\rho(\\omega) = \\frac{N_f}{\\pi} \\frac{\\Delta^*}{(\\omega - \\epsilon^*)^2 + (\\Delta^*)^2}\n$$\n这里，$N_f$ 是杂质能级的简并度。费米能设置为 $\\omega = 0$。参数 $\\epsilon^*$ 和 $\\Delta^*$ 由原始安德森模型的微观参数确定。对于一个正在研究的特定系统，这些参数被发现为：\n$$\n\\epsilon^* = \\Lambda \\sqrt{N_f^2 - 1}\n$$\n$$\n\\Delta^* = \\Lambda\n$$\n其中 $\\Lambda$ 是低能物理的一个特征能标。\n\n杂质对热力学自由能的贡献 $F_{imp}$，用其态密度表示为：\n$$\nF_{imp}(T) = -k_B T \\int_{-\\infty}^{\\infty} d\\omega \\, \\Delta\\rho(\\omega) \\ln\\left(1 + e^{-\\omega/(k_B T)}\\right)\n$$\n其中 $T$ 是温度，$k_B$ 是玻尔兹曼常数。在极低温度下，杂质比热与温度成线性关系，$C_{imp}(T) = \\gamma T$。\n\n你的任务是计算线性比热系数 $\\gamma$。请用 $N_f$、$\\Lambda$ 和 $k_B$ 表示你的答案，形式为一个闭合的解析表达式。", "solution": "线性比热系数 $\\gamma$ 由杂质比热的低温行为定义：$C_{imp}(T) = \\gamma T$。杂质比热由自由能导出：\n\n$$\nC_{imp}(T) = -T \\frac{\\partial^2 F_{imp}}{\\partial T^2}\n$$\n\n其中杂质自由能为：\n\n$$\nF_{imp}(T) = -k_B T \\int_{-\\infty}^{\\infty} d\\omega \\, \\Delta\\rho(\\omega) \\ln\\left(1 + e^{-\\omega/(k_B T)}\\right)\n$$\n\n杂质态密度为：\n\n$$\n\\Delta\\rho(\\omega) = \\frac{N_f}{\\pi} \\frac{\\Delta^*}{(\\omega - \\epsilon^*)^2 + (\\Delta^*)^2}\n$$\n\n参数为：\n\n$$\n\\epsilon^* = \\Lambda \\sqrt{N_f^2 - 1}, \\quad \\Delta^* = \\Lambda\n$$\n\n在极低温度下（$T \\to 0$），适用索末菲展开，比热系数由下式给出：\n\n$$\n\\gamma = \\frac{\\pi^2}{3} k_B^2 \\Delta\\rho(0)\n$$\n\n其中 $\\Delta\\rho(0)$ 是费米能级（$\\omega = 0$）处的态密度。代入 $\\omega = 0$：\n\n$$\n\\Delta\\rho(0) = \\frac{N_f}{\\pi} \\frac{\\Delta^*}{(0 - \\epsilon^*)^2 + (\\Delta^*)^2} = \\frac{N_f}{\\pi} \\frac{\\Lambda}{(-\\Lambda \\sqrt{N_f^2 - 1})^2 + \\Lambda^2}\n$$\n\n简化分母：\n\n$$\n(-\\Lambda \\sqrt{N_f^2 - 1})^2 + \\Lambda^2 = \\Lambda^2 (N_f^2 - 1) + \\Lambda^2 = \\Lambda^2 N_f^2 - \\Lambda^2 + \\Lambda^2 = \\Lambda^2 N_f^2\n$$\n\n因此：\n\n$$\n\\Delta\\rho(0) = \\frac{N_f}{\\pi} \\frac{\\Lambda}{\\Lambda^2 N_f^2} = \\frac{N_f}{\\pi} \\frac{1}{\\Lambda N_f^2} = \\frac{1}{\\pi \\Lambda N_f}\n$$\n\n现在代入 $\\gamma$ 的表达式中：\n\n$$\n\\gamma = \\frac{\\pi^2}{3} k_B^2 \\cdot \\frac{1}{\\pi \\Lambda N_f} = \\frac{\\pi^2 k_B^2}{3 \\pi \\Lambda N_f} = \\frac{\\pi k_B^2}{3 \\Lambda N_f}\n$$", "answer": "$$\n\\boxed{\\dfrac{\\pi k_B^{2}}{3 \\Lambda N_f}}\n$$", "id": "1189270"}, {"introduction": "静态鞍点解描绘了一幅有效的单粒子共振图像，但真实的基态是一个费米液体（Fermi liquid），其中的准粒子之间存在残余相互作用。这些相互作用源于对鞍点解的高斯涨落，在从属玻色子形式中表现为规范场（相位）涨落。此练习将带您超越静态近似，通过计算由规范涨落引起的一阶自能修正，来揭示近藤基态的费米液体本质，并推导出作为其标志的电阻率中 $T^2$ 项的微观来源 [@problem_id:1189266]。", "problem": "在用于对称无限U Anderson杂质模型的Read-Newns路径积分方法中，低能物理通过赝费米子（用$f$表示）来描述，该赝费米子在费米能级处获得一个共振。原始杂质电子的电荷涨落被一个U(1)规范场捕获，该规范场可以等同于一个从属玻色子场的相位。这个规范场的涨落介导了赝费米子之间的相互作用。\n\n赝费米子的自能 $\\Sigma_f$ 可以通过一个单圈图计算，其中一个赝费米子通过发射并重新吸收一个规范玻色子与自身相互作用。在零温（$T=0$）下，能量为 $\\omega$ 的赝费米子的推迟单圈自能的虚部由以下卷积给出：\n$$ \\text{Im} \\Sigma_f^R(\\omega) = \\int_0^{\\omega} \\frac{d\\epsilon}{2\\pi} \\, \\text{Im} D_\\phi^R(\\epsilon) \\, A_f(\\omega - \\epsilon) $$\n其中 $\\omega > 0$。这里，$A_f(\\omega')$ 是无相互作用赝费米子的谱函数，而 $\\text{Im} D_\\phi^R(\\epsilon)$ 是规范玻色子（相位涨落）的推迟传播子的虚部。\n\n对于对称 Anderson 模型，赝费米子谱函数呈现为以费米能级为中心的洛伦兹形式：\n$$ A_f(\\omega') = \\frac{2\\Delta_f}{(\\omega')^2 + \\Delta_f^2} $$\n其中 $\\Delta_f$ 是有效共振宽度，它设定了涌现的低能标度（即近藤温度）。\n\n规范玻色子代表一个过阻尼集体模式。对于小的正能量转移 $\\epsilon > 0$，其传播子的虚部由下式给出：\n$$ \\text{Im} D_\\phi^R(\\epsilon) = -\\gamma_0 \\epsilon $$\n其中 $\\gamma_0$ 是一个表示阻尼强度的正常数。\n\n你的任务是计算赝费米子自能的低频主导行为。假设对于小的 $\\omega \\ll \\Delta_f$，自能具有以下形式\n$$ \\text{Im} \\Sigma_f^R(\\omega) \\approx -K \\omega^2 $$\n请用 $\\Delta_f$ 和 $\\gamma_0$ 表示系数 $K$。", "solution": "我们已知推迟自能虚部的表达式为：\n\n$$\n\\text{Im} \\Sigma_f^R(\\omega) = \\int_0^{\\omega} \\frac{d\\epsilon}{2\\pi} \\, \\text{Im} D_\\phi^R(\\epsilon) \\, A_f(\\omega - \\epsilon)\n$$\n\n其中 $\\omega > 0$。代入给定的形式：\n\n$$\n\\text{Im} D_\\phi^R(\\epsilon) = -\\gamma_0 \\epsilon, \\quad A_f(\\omega') = \\frac{2\\Delta_f}{(\\omega')^2 + \\Delta_f^2}\n$$\n\n积分变为：\n\n$$\n\\text{Im} \\Sigma_f^R(\\omega) = \\int_0^{\\omega} \\frac{d\\epsilon}{2\\pi} \\left( -\\gamma_0 \\epsilon \\right) \\frac{2\\Delta_f}{(\\omega - \\epsilon)^2 + \\Delta_f^2}\n$$\n\n化简得：\n\n$$\n\\text{Im} \\Sigma_f^R(\\omega) = -\\frac{\\gamma_0 \\Delta_f}{\\pi} \\int_0^{\\omega} d\\epsilon \\, \\frac{\\epsilon}{(\\omega - \\epsilon)^2 + \\Delta_f^2}\n$$\n\n对于小的 $\\omega \\ll \\Delta_f$，被积函数可以展开。由于 $\\epsilon \\in [0, \\omega]$ 且 $\\omega \\ll \\Delta_f$，我们有 $(\\omega - \\epsilon)^2 \\ll \\Delta_f^2$。因此，分母主要由 $\\Delta_f^2$ 决定：\n\n$$\n\\frac{1}{(\\omega - \\epsilon)^2 + \\Delta_f^2} \\approx \\frac{1}{\\Delta_f^2} \\left( 1 - \\frac{(\\omega - \\epsilon)^2}{\\Delta_f^2} + \\mathcal{O}\\left( \\frac{(\\omega - \\epsilon)^4}{\\Delta_f^4} \\right) \\right)\n$$\n\n只保留主导项：\n\n$$\n\\frac{\\epsilon}{(\\omega - \\epsilon)^2 + \\Delta_f^2} \\approx \\frac{\\epsilon}{\\Delta_f^2}\n$$\n\n积分简化为：\n\n$$\n\\text{Im} \\Sigma_f^R(\\omega) \\approx -\\frac{\\gamma_0 \\Delta_f}{\\pi} \\int_0^{\\omega} d\\epsilon \\, \\frac{\\epsilon}{\\Delta_f^2} = -\\frac{\\gamma_0}{\\pi \\Delta_f} \\int_0^{\\omega} d\\epsilon \\, \\epsilon\n$$\n\n计算积分：\n\n$$\n\\int_0^{\\omega} \\epsilon  d\\epsilon = \\frac{1}{2} \\omega^2\n$$\n\n所以：\n\n$$\n\\text{Im} \\Sigma_f^R(\\omega) \\approx -\\frac{\\gamma_0}{\\pi \\Delta_f} \\cdot \\frac{1}{2} \\omega^2 = -\\frac{\\gamma_0}{2\\pi \\Delta_f} \\omega^2\n$$\n\n与假设的形式 $\\text{Im} \\Sigma_f^R(\\omega) \\approx -K \\omega^2$ 比较，我们确定：\n\n$$\nK = \\frac{\\gamma_0}{2\\pi \\Delta_f}\n$$", "answer": "$$ \\boxed{\\dfrac{\\gamma_{0}}{2\\pi \\Delta_{f}}} $$", "id": "1189266"}]}