{"hands_on_practices": [{"introduction": "生态位重叠的量化是研究物种间竞争的基石。该练习将指导您使用一个广泛应用的生态学工具——Pianka生态位重叠指数，将关于两个共存捕食者捕食偏好的观测数据，转化为一个衡量潜在竞争强度的具体数值。通过这个计算，您将亲身体验生态学家如何将复杂的生态互动简化为可检验的量化指标。[@problem_id:1887068]", "problem": "在一个稀树草原生态系统中，两种共存的猫科动物，体型较小的Ocelot（*Leopardus pardalis*）和体型较大的Caracal（*Caracal caracal*），表现出资源划分，主要是在猎物大小这一生态位维度上。生态学家发现，对于每个物种，基于猎物质量的猎物利用情况可以由一个正态（高斯）分布精确描述。\n\n对于Ocelot种群，其消耗的猎物质量分布的均值为 $\\mu_O = 3.2$ kg，标准差为 $\\sigma_O = 1.1$ kg。\n对于Caracal种群，该分布的均值为 $\\mu_C = 6.0$ kg，标准差为 $\\sigma_C = 1.8$ kg。\n\n为了量化种间竞争的潜力，生物学家使用生态位重叠指数。对于具有高斯资源利用曲线的两个物种，Pianka生态位重叠指数 $O$ 的取值范围为0（不重叠）到1（完全重叠），其计算公式如下：\n\n$$O = \\sqrt{\\frac{2\\sigma_1 \\sigma_2}{\\sigma_1^2 + \\sigma_2^2}} \\exp\\left(-\\frac{(\\mu_1 - \\mu_2)^2}{2(\\sigma_1^2 + \\sigma_2^2)}\\right)$$\n\n使用为Ocelot和Caracal种群所提供的数据，计算Pianka生态位重叠指数的值。将最终答案四舍五入至三位有效数字。", "solution": "问题要求我们为Ocelot和Caracal这两个物种计算Pianka生态位重叠指数 $O$，这两个物种的资源利用曲线被建模为正态分布。\n\n重叠指数的计算公式如下：\n$$O = \\sqrt{\\frac{2\\sigma_1 \\sigma_2}{\\sigma_1^2 + \\sigma_2^2}} \\exp\\left(-\\frac{(\\mu_1 - \\mu_2)^2}{2(\\sigma_1^2 + \\sigma_2^2)}\\right)$$\n\n让我们从问题陈述中确定物种1（Ocelot）和物种2（Caracal）的参数：\nOcelot的平均猎物质量，$\\mu_1 = \\mu_O = 3.2$ kg。\nOcelot的标准差，$\\sigma_1 = \\sigma_O = 1.1$ kg。\nCaracal的平均猎物质量，$\\mu_2 = \\mu_C = 6.0$ kg。\nCaracal的标准差，$\\sigma_2 = \\sigma_C = 1.8$ kg。\n\n我们将分别计算公式的两个主要部分：平方根前置因子和指数项。\n\n首先，我们来计算指数函数的参数部分：\n$$-\\frac{(\\mu_1 - \\mu_2)^2}{2(\\sigma_1^2 + \\sigma_2^2)}$$\n均值之差为：\n$$\\mu_1 - \\mu_2 = 3.2 - 6.0 = -2.8 \\text{ kg}$$\n该差值的平方为：\n$$(\\mu_1 - \\mu_2)^2 = (-2.8)^2 = 7.84 \\text{ kg}^2$$\n方差之和为：\n$$\\sigma_1^2 + \\sigma_2^2 = (1.1)^2 + (1.8)^2 = 1.21 + 3.24 = 4.45 \\text{ kg}^2$$\n现在，将这些值代入指数的参数部分：\n$$-\\frac{7.84}{2 \\times 4.45} = -\\frac{7.84}{8.90} \\approx -0.880898...$$\n因此，指数项为：\n$$\\exp(-0.880898...) \\approx 0.414407...$$\n\n接下来，我们计算平方根前置因子：\n$$\\sqrt{\\frac{2\\sigma_1 \\sigma_2}{\\sigma_1^2 + \\sigma_2^2}}$$\n我们已经计算出根号内分数的分母：$\\sigma_1^2 + \\sigma_2^2 = 4.45$ kg$^2$。\n分子为：\n$$2\\sigma_1 \\sigma_2 = 2 \\times 1.1 \\times 1.8 = 3.96 \\text{ kg}^2$$\n根号内的分数为：\n$$\\frac{3.96}{4.45} \\approx 0.889887...$$\n前置因子是该值的平方根：\n$$\\sqrt{0.889887...} \\approx 0.943338...$$\n\n最后，我们将前置因子与指数项相乘，得到重叠指数 $O$：\n$$O = (0.943338...) \\times (0.414407...) \\approx 0.39093...$$\n\n问题要求将最终答案四舍五入至三位有效数字。\n$$O \\approx 0.391$$", "answer": "$$\\boxed{0.391}$$", "id": "1887068"}, {"introduction": "我们对物种生态位的理解，有时会随着生物学新发现（如隐存种的揭示）而发生颠覆性改变。本练习将带领您应用Levins指数来计算生态位宽度，并探讨一个深刻的生态学现象：一个看似“广食性”的物种，实际上可能由多个“专食性”的隐存种构成。这个实践案例突显了精确的物种鉴定在生态位研究中的重要性，以及它如何影响我们对群落结构的认知。[@problem_id:1887038]", "problem": "一位生态学家正在研究一种广泛分布的蛾类——*Phalaena ficta*——在混交落叶林中的资源利用情况。该生态学家对种群进行取样，并记录了利用五种不同寄主植物物种的个体数量。生态位宽度是衡量一个物种所利用资源多样性的指标，可以使用 Levins 指数 $B$ 来量化，其计算公式为：\n$$B = \\frac{1}{\\sum_{i=1}^{R} p_i^2}$$\n其中，$R$ 是资源类别的总数（在此案例中为寄主植物物种），$p_i$ 是发现利用资源类别 $i$ 的物种个体所占的比例。\n\n最初，生态学家为假定为单一物种 *Phalaena ficta* 收集了以下数据：\n- 寄主植物 1：250 个个体\n- 寄主植物 2：250 个个体\n- 寄主植物 3：200 个个体\n- 寄主植物 4：150 个个体\n- 寄主植物 5：150 个个体\n\n随后的遗传分析揭示了一个惊人的发现：*P. ficta* 并非单一物种，而是由两个形态上相同但生殖隔离的隐存种（物种A和物种B）组成。生态学家使用遗传标记重新分析了原始样本，并能够将每个个体分配到其正确的物种。每种特化物种的寄主植物利用情况的新分解如下：\n\n**物种A：**\n- 寄主植物 1：200 个个体\n- 寄主植物 2：200 个个体\n- 寄主植物 3：50 个个体\n- 寄主植物 4：25 个个体\n- 寄主植物 5：25 个个体\n\n**物种B：**\n- 寄主植物 1：50 个个体\n- 寄主植物 2：50 个个体\n- 寄主植物 3：150 个个体\n- 寄主植物 4：125 个个体\n- 寄主植物 5：125 个个体\n\n您的任务是量化这一发现导致的生态位结构评估的变化。计算两种特化物种（物种A和物种B）的生态位宽度之和与最初被认为是泛化物种（*P. ficta*）的生态位宽度之比。将您的答案表示为一个无量纲比率，并四舍五入到三位有效数字。", "solution": "问题要求计算比率 $(B_A + B_B) / B_{total}$，其中 $B_{total}$ 是为初始“泛化”种群计算的生态位宽度，$B_A$ 和 $B_B$ 是为两种新发现的特化物种计算的生态位宽度。生态位宽度使用 Levins 指数计算：$B = 1 / \\sum_{i=1}^{R} p_i^2$。\n\n**步骤1：计算原始“泛化”物种（*P. ficta*）的生态位宽度 $B_{total}$。**\n\n首先，我们找出取样的个体总数：\n$N_{total} = 250 + 250 + 200 + 150 + 150 = 1000$\n\n接下来，我们计算每种寄主植物上个体的比例 $p_i$：\n$p_1 = 250 / 1000 = 0.25$\n$p_2 = 250 / 1000 = 0.25$\n$p_3 = 200 / 1000 = 0.20$\n$p_4 = 150 / 1000 = 0.15$\n$p_5 = 150 / 1000 = 0.15$\n\n现在，我们计算这些比例的平方和 $\\sum p_i^2$：\n$\\sum p_{total}^2 = (0.25)^2 + (0.25)^2 + (0.20)^2 + (0.15)^2 + (0.15)^2$\n$\\sum p_{total}^2 = 0.0625 + 0.0625 + 0.0400 + 0.0225 + 0.0225 = 0.2100$\n\n最后，我们计算 $B_{total}$：\n$B_{total} = \\frac{1}{\\sum p_{total}^2} = \\frac{1}{0.2100} \\approx 4.76190$\n\n**步骤2：计算物种A的生态位宽度 $B_A$。**\n\n首先，我们找出物种A的个体总数：\n$N_A = 200 + 200 + 50 + 25 + 25 = 500$\n\n接下来，我们计算物种A的比例 $p_{A,i}$：\n$p_{A,1} = 200 / 500 = 0.40$\n$p_{A,2} = 200 / 500 = 0.40$\n$p_{A,3} = 50 / 500 = 0.10$\n$p_{A,4} = 25 / 500 = 0.05$\n$p_{A,5} = 25 / 500 = 0.05$\n\n现在，计算 $\\sum p_{A,i}^2$：\n$\\sum p_A^2 = (0.40)^2 + (0.40)^2 + (0.10)^2 + (0.05)^2 + (0.05)^2$\n$\\sum p_A^2 = 0.1600 + 0.1600 + 0.0100 + 0.0025 + 0.0025 = 0.3350$\n\n最后，我们计算 $B_A$：\n$B_A = \\frac{1}{\\sum p_A^2} = \\frac{1}{0.3350} \\approx 2.98507$\n\n**步骤3：计算物种B的生态位宽度 $B_B$。**\n\n首先，我们找出物种B的个体总数：\n$N_B = 50 + 50 + 150 + 125 + 125 = 500$\n（作为核对，$N_A + N_B = 500 + 500 = 1000 = N_{total}$，这是正确的。）\n\n接下来，我们计算物种B的比例 $p_{B,i}$：\n$p_{B,1} = 50 / 500 = 0.10$\n$p_{B,2} = 50 / 500 = 0.10$\n$p_{B,3} = 150 / 500 = 0.30$\n$p_{B,4} = 125 / 500 = 0.25$\n$p_{B,5} = 125 / 500 = 0.25$\n\n现在，计算 $\\sum p_{B,i}^2$：\n$\\sum p_B^2 = (0.10)^2 + (0.10)^2 + (0.30)^2 + (0.25)^2 + (0.25)^2$\n$\\sum p_B^2 = 0.0100 + 0.0100 + 0.0900 + 0.0625 + 0.0625 = 0.2350$\n\n最后，我们计算 $B_B$：\n$B_B = \\frac{1}{\\sum p_B^2} = \\frac{1}{0.2350} \\approx 4.25532$\n\n**步骤4：计算最终比率。**\n\n问题要求计算比率 $\\frac{B_A + B_B}{B_{total}}$。\n首先，将特化物种的生态位宽度相加：\n$B_A + B_B \\approx 2.98507 + 4.25532 = 7.24039$\n\n现在，计算该比率：\n比率 $= \\frac{B_A + B_B}{B_{total}} \\approx \\frac{7.24039}{4.76190} \\approx 1.52048$\n\n四舍五入到三位有效数字，我们得到 1.52。这个结果表明，两种特化物种的生态位宽度之和比被认为是泛化物种的生态位宽度大约 52% 。这种泛化物种的生态位宽度小于其所包含的特化物种生态位宽度之和的现象，是生态位宽度计算方式的一个已知结果，反映了特化物种更集中的资源利用方式。", "answer": "$$\\boxed{1.52}$$", "id": "1887038"}, {"introduction": "在生态学研究中，观察到物种间的负相互作用仅仅是第一步，真正的挑战在于揭示其背后的驱动机制。这个思想实验将挑战您超越简单的观察，设计一个严谨的野外实验方案，以区分直接的资源竞争与由共享捕食者介导的间接“似然竞争”。这不仅是对生态位概念的深化理解，更是对科学方法论中实验设计能力的综合考验。[@problem_id:1887106]", "problem": "一位生态学家正在研究草原生态系统恢复的动态。两种本土丛生禾本科物种，物种A和物种B，被种植在实验样地中。在隔离种植时，两种物种都生长旺盛。然而，在该区域被一种引入的广食性食草动物Fallow Deer意外定殖后，生态学家观察到，与仅包含物种A或仅包含物种B的样地相比，同时包含A和B的样地中，两种草的生物量都出现了更快、更严重的下降。为解释这种在物种共存时出现的加剧性下降，提出了两个主要假说：\n\n1.  **加剧的资源竞争 (Exacerbated Resource Competition):** Fallow Deer偏好取食长势最旺盛的植物。这种选择性取食削弱了物种A和物种B，降低了它们竞争土壤氮和水等限制性资源的能力。食草作用和加剧的资源竞争的双重胁迫导致了两者的迅速衰退。\n2.  **似然竞争 (Apparent Competition):** 这两种草类物种之间没有显著的资源竞争。相反，混合物种样地中较高的总植物生物量供养了一个更大、更集中的鹿种群。这种增加的食草动物密度导致了对两种物种的总体取食压力增大，从而引起它们的共同衰退。这种竞争是“似然的”，因为这两个物种仅通过它们共同的捕食者对彼此产生负面影响。\n\n您的任务是设计一个野外实验，以明确确定这两种机制中哪一种是观测到的衰退的主要驱动因素。从以下选项中，哪一个实验设计在区分加剧的资源竞争和似然竞争方面最为稳健和完整？假设您可以使用一个大而均质的田地区域和足够的围栏材料来建造能防止食草动物进入的围栏。\n\nA. 建立两种主要处理：同时包含物种A和B的样地，以及仅包含物种A的样地。在每种处理的一半样地中，施用富含氮的肥料。监测草的生物量。这直接检验了养分限制的作用。\n\nB. 设置一系列相同的混合物种样地（包含A和B）。在这些样地中引入不同种群密度的Fallow Deer。监测两种草的生物量随鹿密度变化的下降情况。\n\nC. 以物种A为焦点物种，采用全因子设计，包含两个因子：物种B的存在/缺失，以及Fallow Deer的存在/缺失。这会产生四种不同的处理类型：(1) 仅有物种A，排除鹿；(2) 物种A与物种B共存，排除鹿；(3) 仅有物种A，有鹿存在；(4) 物种A与物种B共存，有鹿存在。整个实验设置将以物种B为焦点物种进行重复。\n\nD. 建立三种类型的大型开放样地，鹿可自由进入：仅有物种A的样地，仅有物种B的样地，以及同时包含物种A和B的样地。在几个生长季内监测所有样地中草的生物量。\n\nE. 在受控的温室环境中种植物种A和物种B。在花盆中设置两种竞争处理：单独种植物种A，以及物种A与物种B共同种植。对每种处理，通过定期剪掉固定百分比的植物生物量来模拟食草作用。测量最终植物生物量。", "solution": "为每个焦点物种 $X \\in \\{A,B\\}$ 定义平均生物量响应 $B_{X}(N,D)$，其中 $N \\in \\{0,1\\}$ 表示异种邻居的缺失(0)或存在(1)，而 $D \\in \\{0,1\\}$ 表示鹿被排除(0)或鹿存在(1)。这两个假说对这些处理平均值之间的差异做出了独特且可检验的预测。\n\n在似然竞争假说下：\n1) 机制：负面效应完全由共享的食草动物介导，通过其对更高总生物量的聚集反应或数量反应产生；几乎没有直接的资源竞争。\n2) 预测：\n   a) 当鹿被排除时，邻居的存在应该具有可忽略不计的影响：\n   $$\n   B_{X}(1,0) \\approx B_{X}(0,0).\n   $$\n   b) 当鹿存在时，邻居的存在会降低焦点物种的生物量，因为混合样地会吸引或维持更高的鹿密度压力：\n   $$\n   B_{X}(1,1) < B_{X}(0,1).\n   $$\n   c) 因此，邻居效应强烈依赖于鹿的存在。就交互作用对比而言，\n   $$\n   \\left[B_{X}(0,1)-B_{X}(1,1)\\right]-\\left[B_{X}(0,0)-B_{X}(1,0)\\right] < 0,\n   $$\n   且 $B_{X}(0,0)-B_{X}(1,0) \\approx 0$。\n\n在加剧的资源竞争假说下：\n1) 机制：鹿削弱了植物，增加了资源限制的强度并加剧了种间竞争；即使没有鹿，也存在直接的资源竞争，但食草作用会放大这种竞争。\n2) 预测：\n   a) 当鹿被排除时，由于资源竞争，邻居的存在会降低焦点物种的生物量：\n   $$\n   B_{X}(1,0) < B_{X}(0,0).\n   $$\n   b) 当鹿存在时，负面的邻居效应更大（一种放大效应）：\n   $$\n   \\left[B_{X}(0,1)-B_{X}(1,1)\\right] > \\left[B_{X}(0,0)-B_{X}(1,0)\\right] > 0.\n   $$\n   c) 因此，存在一个显著的交互作用，即鹿的存在增加了邻居效应的强度，但重要的是，当鹿被排除时，邻居效应已经存在。\n\n一个最稳健和最完整的野外设计必须：\n- 将邻居存在/缺失和鹿存在/缺失作为完全交叉的因子，以评估它们对每个焦点物种的主效应及其交互作用。\n- 对每个物种作为焦点物种进行重复，以检测不对称性。\n- 允许直接检验负面的邻居效应是否在没有鹿的情况下持续存在（直接资源竞争），还是仅在有鹿时才出现（似然竞争），以及鹿是否放大了已有的竞争效应。\n\n选项C精确地为每个焦点物种实施了这种全因子设计：\n- 对焦点物种 $X$ 的处理：$(N,D) \\in \\{(0,0),(1,0),(0,1),(1,1)\\}$，并进行重复。\n- 诊断性对比：\n  1) 检验没有鹿时的直接资源竞争：$B_{X}(0,0)$ vs. $B_{X}(1,0)$。\n  2) 检验没有邻居时的鹿效应：$B_{X}(0,0)$ vs. $B_{X}(0,1)$。\n  3) 检验似然竞争：邻居效应仅在 $D=1$ 时出现，即 $B_{X}(1,1) < B_{X}(0,1)$ 但 $B_{X}(1,0) \\approx B_{X}(0,0)$。\n  4) 检验加剧的资源竞争：在 $D=0$ 时存在一个负面的邻居效应，并且在 $D=1$ 时该效应被加强，即 $B_{X}(1,0) < B_{X}(0,0)$ 且 $\\left[B_{X}(0,1)-B_{X}(1,1)\\right] > \\left[B_{X}(0,0)-B_{X}(1,0)\\right]$。\n\n相比之下：\n- A操纵了养分但没有操纵食草动物的存在，因此它无法将似然竞争与食草动物放大的竞争分离开来，并且忽略了邻居与鹿之间完整的交互作用。\n- B仅在混合样地中改变鹿的密度，缺乏识别直接竞争以及将效应明确归因于似然竞争所需的缺失邻居的对照。\n- D比较了有鹿存在时的单一栽培与混合栽培，但缺少排除鹿的对照，因此混淆了不同的机制。\n- E使用温室修剪，这无法产生鹿的聚集反应或数量反应，因此无法检验似然竞争。\n\n因此，选项C是在该系统中区分加剧的资源竞争和似然竞争的最稳健和最完整的设计。", "answer": "$$\\boxed{C}$$", "id": "1887106"}]}