{"hands_on_practices": [{"introduction": "在合成生物学中，将报告基因（如荧光蛋白）的输出信号与细胞密度（通常通过光密度$OD$测量）进行归一化，是量化基因表达活性的基本操作。然而，任何实验测量都伴随着不确定性。本练习将指导您掌握一项至关重要的技能：当您用一个测量值除以另一个测量值时，如何正确地计算最终结果的不确定性，这对于评估我们归一化启动子活性的可信度至关重要。[@problem_id:2061652]", "problem": "一位合成生物学家正在表征一个新设计的启动子在 *E. coli* 底盘中的强度。实验设置涉及一个质粒，该质粒上的启动子驱动一个绿色荧光蛋白 (GFP) 报告基因的表达。启动子的强度通过测量细菌培养物的荧光并用细胞密度对其进行归一化来量化。\n\n细胞密度通过测量 600 nm 处的光密度 (OD) 来估计。归一化荧光 $Y$ 计算为扣除背景后的平均荧光强度 $F$ 与平均 OD 的比率，即 $Y = F/OD$。\n\n在特定诱导条件下，通过一系列重复测量，该生物学家获得了以下的平均值和标准差，它们被视为测量值及其绝对不确定度：\n- 平均荧光强度，$F = 9.52 \\times 10^4$ 任意单位。\n- 荧光不确定度，$\\sigma_F = 3.80 \\times 10^3$ 任意单位。\n- 平均光密度，$OD = 0.760$。\n- 光密度不确定度，$\\sigma_{OD} = 0.015$。\n\n假设荧光和光密度的测量是独立的，计算归一化荧光的绝对不确定度 $\\sigma_Y$。将结果以“任意单位/OD单位”为单位表示，并四舍五入到三位有效数字。", "solution": "我们将归一化荧光定义为 $Y = \\frac{F}{OD}$。对于独立测量值 $F$ 和 $OD$，函数 $Y(F,OD)$ 的标准不确定度传播公式为\n$$\n\\sigma_{Y}^{2} = \\left(\\frac{\\partial Y}{\\partial F}\\right)^{2}\\sigma_{F}^{2} + \\left(\\frac{\\partial Y}{\\partial OD}\\right)^{2}\\sigma_{OD}^{2}.\n$$\n对于 $Y = \\frac{F}{OD}$，其偏导数为\n$$\n\\frac{\\partial Y}{\\partial F} = \\frac{1}{OD}, \\qquad \\frac{\\partial Y}{\\partial OD} = -\\frac{F}{OD^{2}}.\n$$\n因此，\n$$\n\\sigma_{Y} = \\sqrt{\\left(\\frac{\\sigma_{F}}{OD}\\right)^{2} + \\left(\\frac{F\\,\\sigma_{OD}}{OD^{2}}\\right)^{2}}.\n$$\n等效地，以相对形式表示，\n$$\n\\frac{\\sigma_{Y}}{Y} = \\sqrt{\\left(\\frac{\\sigma_{F}}{F}\\right)^{2} + \\left(\\frac{\\sigma_{OD}}{OD}\\right)^{2}}, \\qquad Y = \\frac{F}{OD}.\n$$\n\n代入给定值：\n- $F = 9.52 \\times 10^{4}$，$\\sigma_{F} = 3.80 \\times 10^{3}$，\n- $OD = 0.760$，$\\sigma_{OD} = 0.015$。\n\n首先计算 $Y$（为了方便使用相对形式）：\n$$\nY = \\frac{9.52 \\times 10^{4}}{0.760} = \\frac{95{,}200}{0.760} = 1.252631578947368 \\times 10^{5}.\n$$\n计算相对不确定度：\n$$\n\\frac{\\sigma_{F}}{F} = \\frac{3.80 \\times 10^{3}}{9.52 \\times 10^{4}} = \\frac{3800}{95200} = \\frac{19}{476},\n$$\n$$\n\\frac{\\sigma_{OD}}{OD} = \\frac{0.015}{0.760} = \\frac{3}{152}.\n$$\n合成相对不确定度：\n$$\n\\sqrt{\\left(\\frac{19}{476}\\right)^{2} + \\left(\\frac{3}{152}\\right)^{2}} = \\sqrt{\\frac{361}{226{,}576} + \\frac{9}{23{,}104}} = \\sqrt{\\frac{648{,}733}{327{,}175{,}744}} \\approx 4.4529 \\times 10^{-2}.\n$$\n因此，\n$$\n\\sigma_{Y} = Y \\times \\sqrt{\\left(\\frac{\\sigma_{F}}{F}\\right)^{2} + \\left(\\frac{\\sigma_{OD}}{OD}\\right)^{2}} \\approx \\left(1.252631578947368 \\times 10^{5}\\right)\\left(4.4529 \\times 10^{-2}\\right) \\approx 5.58 \\times 10^{3}.\n$$\n四舍五入到三位有效数字，归一化荧光的绝对不确定度为 $5.58 \\times 10^{3}$ 任意单位/OD单位。", "answer": "$$\\boxed{5.58 \\times 10^{3}}$$", "id": "2061652"}, {"introduction": "尽管通过光密度$OD$进行归一化是一种强大的技术，但它有其局限性，特别是在高细胞密度下。此时，一种称为“内滤效应”的物理伪影会显著影响测量结果的准确性，导致荧光信号与细胞数量之间出现非线性关系。本练习提供了一个基于物理原理的模型，帮助您理解并量化这种效应，这对于从密集的细胞培养物中获取可靠的定量数据非常关键。[@problem_id:2061643]", "problem": "在一个合成生物学实验中，一名研究人员正在量化高密度细菌培养物中绿色荧光蛋白 (GFP) 的表达。从培养物中测得的总荧光强度被用作所产生蛋白质总量的衡量指标。在低细胞密度下，测得的总荧光强度与细胞浓度成正比。然而，在高细胞密度下，由于“内滤效应”，这种线性关系被打破。在内滤效应中，细胞本身会吸收射入的激发光和射出的荧光。\n\n为了对此进行建模，我们考虑在一个内部边长为 $L$ 的方形底比色皿中进行测量。强度均匀的激发光束从比色皿的一个面（位于 $x=0$ 处的 $y-z$ 平面）射入，并沿x轴传播。荧光发射沿y轴方向，通过位于 $y=L$ 处的 $x-z$ 平面上的面被检测。该细菌培养物的特征是其在600纳米处的光密度（OD），记作 $D_{600}$，这是使用标准1厘米光程测量的。\n\n培养物对光的衰减遵循比尔-朗伯定律。在激发波长和发射波长处，培养物的有效每厘米光密度是不同的。\n- 在激发波长处的每厘米光密度 $A_{ex}$ 与细胞密度的关系为 $A_{ex} = f_{ex} D_{600}$。\n- 在发射波长处的每厘米光密度 $A_{em}$ 与细胞密度的关系为 $A_{em} = f_{em} D_{600}$。\n\n“理想总荧光” $F_{ideal}$ 定义为在培养物对激发光和发射光均透明的情况下（即，在细胞密度为零的极限下，但每个细胞的荧光强度相同）所能测得的荧光。实际测得的荧光为 $F_{measured}$。\n\n对于一个 $D_{600} = 2.0$ 的培养物，在 $L = 1.0$ 厘米的比色皿中测量，使用因子 $f_{ex} = 1.25$ 和 $f_{em} = 1.10$，计算校正因子 $\\eta = \\frac{F_{measured}}{F_{ideal}}$。该比率表示在没有吸收效应的理想情况下，实际检测到的荧光信号所占的比例。\n\n将您的最终答案四舍五入到三位有效数字。", "solution": "以10为底的光密度形式的比尔-朗伯定律给出，在位置 $x$ 处的激发光强度为 $I_{ex}(x) = I_{0} 10^{-A_{ex} x}$，其中 $A_{ex}$ 是激发波长处的每厘米光密度。在点 $(x,y,z)$ 处产生的荧光与局部激发光强度成正比，而沿 $+y$ 方向朝向检测器传播的发射光在光程 $(L - y)$ 上被衰减一个因子 $10^{-A_{em}(L-y)}$，其中 $A_{em}$ 是发射波长处的每厘米光密度。\n\n令 $C$ 代表所有比例常数（包括荧光团密度、量子产率、检测效率，以及在测量情况和理想情况下都共有的几何因子）。那么，检测到的荧光为\n$$\nF_{measured} = C \\int_{0}^{L} \\int_{0}^{L} \\int_{0}^{L} I_{0} 10^{-A_{ex} x} 10^{-A_{em}(L-y)} \\, dz \\, dy \\, dx.\n$$\n在理想的透明情况下（在任一波长下均无衰减），检测到的荧光为\n$$\nF_{ideal} = C \\int_{0}^{L} \\int_{0}^{L} \\int_{0}^{L} I_{0} \\, dz \\, dy \\, dx = C I_{0} L^{3}.\n$$\n因此，校正因子为\n$$\n\\eta = \\frac{F_{measured}}{F_{ideal}} = \\frac{1}{L^{3}} \\int_{0}^{L} \\int_{0}^{L} \\int_{0}^{L} 10^{-A_{ex} x} 10^{-A_{em}(L-y)} \\, dz \\, dy \\, dx.\n$$\n被积函数与 $z$ 无关，因此产生一个因子 $L$，所以\n$$\n\\eta = \\frac{1}{L^{2}} \\left( \\int_{0}^{L} 10^{-A_{ex} x} \\, dx \\right) \\left( \\int_{0}^{L} 10^{-A_{em}(L-y)} \\, dy \\right).\n$$\n使用 $\\int 10^{k x} \\, dx = \\frac{1}{k \\ln 10} 10^{k x}$，我们得到\n$$\n\\int_{0}^{L} 10^{-A_{ex} x} \\, dx = \\frac{1 - 10^{-A_{ex} L}}{A_{ex} \\ln 10}, \\quad\n\\int_{0}^{L} 10^{-A_{em}(L-y)} \\, dy = \\frac{1 - 10^{-A_{em} L}}{A_{em} \\ln 10}.\n$$\n因此\n$$\n\\eta = \\frac{1}{L^{2}} \\frac{\\left(1 - 10^{-A_{ex} L}\\right)\\left(1 - 10^{-A_{em} L}\\right)}{A_{ex} A_{em} (\\ln 10)^{2}}.\n$$\n已知 $A_{ex} = f_{ex} D_{600}$ 和 $A_{em} = f_{em} D_{600}$，并代入给定值 $D_{600} = 2.0$，$L = 1.0$，$f_{ex} = 1.25$，$f_{em} = 1.10$，我们有\n$$\nA_{ex} = 2.5, \\quad A_{em} = 2.2, \\quad A_{ex} L = 2.5, \\quad A_{em} L = 2.2.\n$$\n于是\n$$\n\\eta = \\frac{\\left(1 - 10^{-2.5}\\right)\\left(1 - 10^{-2.2}\\right)}{(2.5)(2.2)(\\ln 10)^{2}}.\n$$\n数值计算上，$10^{-2.5} \\approx 0.00316227766$，$10^{-2.2} \\approx 0.00630957344$，所以\n$$\n\\left(1 - 10^{-2.5}\\right)\\left(1 - 10^{-2.2}\\right) \\approx 0.990548102,\n$$\n并且 $(\\ln 10)^{2} \\approx 5.30189811$，\n$$\n(2.5)(2.2)(\\ln 10)^{2} \\approx 29.1604396,\n$$\n得到\n$$\n\\eta \\approx \\frac{0.990548102}{29.1604396} \\approx 0.0339689.\n$$\n四舍五入到三位有效数字，$\\eta \\approx 0.0340$。", "answer": "$$\\boxed{0.0340}$$", "id": "2061643"}, {"introduction": "为了更精确地量化基因表达，研究人员常采用更高级的策略，例如使用双报告系统，即用一个稳定表达的荧光蛋白来校正细胞间在蛋白合成能力上的差异。然而，这种多色荧光测量方法引入了其自身的技术挑战，即“光谱串扰”，其中一个荧光蛋白的信号会“泄漏”到另一个的检测通道中。本练习将引导您完成一个标准的数据校正流程，以消除细胞自发荧光和光谱串扰的影响，从而精确地解析出真实的基因表达水平，这是现代定量生物学中一项不可或缺的技能。[@problem_id:2061624]", "problem": "在一个合成生物学实验中，一位研究人员旨在量化 *E. coli* 中一个诱导型启动子（$P_{ind}$）的活性。为此，他们构建了一个质粒，其中绿色荧光蛋白（GFP）的基因被置于 $P_{ind}$ 的调控之下。为了对细胞间蛋白质合成能力的差异（例如，由于细胞大小或代谢状态的差异）进行归一化，他们共转化了第二个质粒。这个质粒含有一个红色荧光蛋白 mCherry 的基因，该基因受一个强的组成型启动子调控，用作全局蛋白质合成速率的代表指标。\n\n研究人员使用成像流式细胞仪分析了几个细菌群体，该仪器测量了单个细胞在绿色和红色检测通道中的总积分荧光强度。所有测量值均以任意单位（a.u.）报告。\n\n从至少 $10^5$ 个细胞的群体中获得了以下平均荧光强度值：\n\n1.  **野生型细胞 (WT):** 这些细胞不含荧光蛋白，用于测量基线细胞自发荧光。\n    - 绿色通道中的平均强度：$I_G^{WT} = 150$ a.u.\n    - 红色通道中的平均强度：$I_R^{WT} = 50$ a.u.\n\n2.  **仅含 mCherry 的细胞:** 这些细胞仅从组成型启动子表达 mCherry，用于量化 mCherry 荧光到绿色通道的光谱串扰（渗漏）。\n    - 绿色通道中的平均强度：$I_G^{mCherry} = 750$ a.u.\n    - 红色通道中的平均强度：$I_R^{mCherry} = 10050$ a.u.\n\n3.  **双报告基因细胞:** 这些细胞同时表达 GFP（在诱导后由 $P_{ind}$ 表达）和 mCherry。\n    - 绿色通道中的平均强度：$I_G^{dual} = 8320$ a.u.\n    - 红色通道中的平均强度：$I_R^{dual} = 12050$ a.u.\n\n您的任务是计算 $P_{ind}$ 启动子的归一化输出。这被定义为双报告基因细胞群体中真实 GFP 荧光与真实 mCherry 荧光的比率。假设从 mCherry 到 GFP 通道的光谱渗漏是 mCherry 荧光强度的线性函数，并且从 GFP 到 mCherry 通道没有明显的渗漏。\n\n计算归一化的启动子输出。将您的最终答案四舍五入到三位有效数字。", "solution": "目标是计算归一化的启动子输出，即细胞的真实绿色荧光蛋白（GFP）荧光与真实 mCherry 荧光的比率。我们将真实 GFP 荧光表示为 $F_{GFP}$，真实 mCherry 荧光表示为 $F_{mCherry}$。所求的量为 $R_{norm} = \\frac{F_{GFP}}{F_{mCherry}}$。\n\n流式细胞仪中测得的强度受到两个主要因素的影响：细胞自发荧光和光谱串扰。我们必须对这两者进行校正，以找到真实的荧光值。\n\n**步骤 1：校正自发荧光**\n\n任何通道中测得的总强度是报告蛋白的荧光与细胞自然自发荧光之和。我们可以通过减去野生型（WT）细胞的平均强度来计算任何群体的背景扣除后荧光。\n设 $I'_X$ 为通道 $X \\in \\{G, R\\}$ 中背景扣除后的强度。\n\n对于仅含 mCherry 的细胞，背景扣除后的强度为：\n$I'_G{}^{mCherry} = I_G^{mCherry} - I_G^{WT} = 750 - 150 = 600$ a.u.\n$I'_R{}^{mCherry} = I_R^{mCherry} - I_R^{WT} = 10050 - 50 = 10000$ a.u.\n\n对于双报告基因细胞，背景扣除后的强度为：\n$I'_G{}^{dual} = I_G^{dual} - I_G^{WT} = 8320 - 150 = 8170$ a.u.\n$I'_R{}^{dual} = I_R^{dual} - I_R^{WT} = 12050 - 50 = 12000$ a.u.\n\n**步骤 2：量化光谱串扰**\n\n仅含 mCherry 的细胞使我们能够确定“渗漏”到绿色检测通道中的 mCherry 荧光的比例。在这个群体中，没有 GFP，因此绿色通道中任何背景扣除后的信号都必须来自 mCherry。\n仅含 mCherry 细胞中的真实 mCherry 荧光是红色通道中背景扣除后的信号：$F_{mCherry}^{control} = I'_R{}^{mCherry} = 10000$ a.u。\n绿色通道中的渗漏信号为 $I'_{G, bleed} = I'_G{}^{mCherry} = 600$ a.u。\n\n线性串扰系数 $\\alpha$ 是绿色通道中的渗漏信号与红色通道中真实信号的比率。\n$$ \\alpha = \\frac{I'_{G, bleed}}{F_{mCherry}^{control}} = \\frac{I'_G{}^{mCherry}}{I'_R{}^{mCherry}} = \\frac{600}{10000} = 0.06 $$\n这意味着每 100 a.u. 的真实 mCherry 荧光，就有 6 a.u. 会被错误地在绿色通道中检测到。\n\n**步骤 3：计算双报告基因细胞中的真实荧光**\n\n现在我们可以使用已确定的参数来计算双报告基因细胞中的真实荧光值。\n\n问题陈述中提到，从 GFP 到红色通道没有明显的渗漏。因此，双报告基因细胞中的真实 mCherry 荧光就是红色通道中背景扣除后的强度。\n$$ F_{mCherry} = I'_R{}^{dual} = 12000 \\text{ a.u.} $$\n\n绿色通道中背景扣除后的强度 $I'_G{}^{dual}$ 是真实 GFP 荧光 $F_{GFP}$ 与同样存在于这些细胞中的 mCherry 荧光产生的串扰之和。\n$$ I'_G{}^{dual} = F_{GFP} + (\\alpha \\times F_{mCherry}) $$\n\n我们现在可以求解真实 GFP 荧光 $F_{GFP}$：\n$$ F_{GFP} = I'_G{}^{dual} - (\\alpha \\times F_{mCherry}) $$\n代入数值：\n$$ F_{GFP} = 8170 - (0.06 \\times 12000) $$\n$$ F_{GFP} = 8170 - 720 = 7450 \\text{ a.u.} $$\n\n**步骤 4：计算归一化的启动子输出**\n\n归一化的启动子输出是真实 GFP 荧光与真实 mCherry 荧光的比率。\n$$ R_{norm} = \\frac{F_{GFP}}{F_{mCherry}} = \\frac{7450}{12000} $$\n$$ R_{norm} = 0.6208333... $$\n\n四舍五入到三位有效数字，我们得到：\n$$ R_{norm} \\approx 0.621 $$", "answer": "$$\\boxed{0.621}$$", "id": "2061624"}]}