{
    "hands_on_practices": [
        {
            "introduction": "质谱分析的核心在于根据质荷比 ($m/z$) 对离子进行分离。在飞行时间（TOF）分析器中，这是通过精确测量离子飞越已知距离所需的时间来实现的。这个练习将带您深入了解 MALDI-TOF 质谱的物理心脏，通过计算两个质量相近的蛋白质离子之间微小的飞行时间差异，您将亲身体会到该技术对时间和质量分辨率的极致要求 。",
            "id": "5130507",
            "problem": "在用于微生物鉴定的基质辅助激光解吸/电离 (MALDI) 飞行时间 (TOF) 质谱法中，单电荷核糖体蛋白离子通过长度为 $L$ 的无场飞行管，由加速电压 $V$ 加速。假设一个带电荷 $q=e$（元电荷）的单电荷离子，其从电势中获得的动能为 $qV$，漂移速度 $v$ 满足 $\\frac{1}{2} m v^{2} = q V$。飞行时间 (TOF) 于是为 $t = \\frac{L}{v} = L \\sqrt{\\frac{m}{2 q V}}$。\n\n考虑两个细菌核糖体蛋白离子，其质量分别为 $5 \\, \\mathrm{kDa}$ 和 $5.05 \\, \\mathrm{kDa}$，在长度为 $L = 1.2 \\, \\mathrm{m}$、加速电压为 $V = 20 \\, \\mathrm{kV}$ 的飞行管中被加速。假设为单电荷离子（$q=e$），并使用统一原子质量单位换算 $1 \\, \\mathrm{Da} = 1.66053906660 \\times 10^{-27} \\, \\mathrm{kg}$ 以及 $e = 1.602176634 \\times 10^{-19} \\, \\mathrm{C}$。计算这两个离子之间预期的飞行时间差 $\\Delta t$。将最终答案以纳秒为单位表示，并四舍五入到四位有效数字。\n\n简要说明您计算出的 $\\Delta t$ 与在这些质量下进行物种区分所需的最低时域分辨能力之间的关系，但不要提供第二个数值答案。",
            "solution": "问题陈述经核实具有科学依据，提法恰当，客观且完整。所有必要的物理原理、常数和参数均已提供，足以计算出唯一且有意义的解。用于微生物鉴定的基质辅助激光解吸/电离飞行时间 (MALDI-TOF) 质谱法的背景是恰当的，给定的数值在物理上是现实的。\n\n质量为 $m$、电荷为 $q$ 的离子在长度为 $L$ 的飞行管中被电压 $V$ 加速，其飞行时间 $t$ 由以下公式给出：\n$$t = L \\sqrt{\\frac{m}{2qV}}$$\n我们已知两个不同的蛋白质离子，质量分别为 $m_1$ 和 $m_2$。它们各自的飞行时间 $t_1$ 和 $t_2$ 分别是：\n$$t_1 = L \\sqrt{\\frac{m_1}{2qV}}$$\n$$t_2 = L \\sqrt{\\frac{m_2}{2qV}}$$\n问题要求计算它们的飞行时间差 $\\Delta t = t_2 - t_1$。我们可以将其表示为：\n$$\\Delta t = t_2 - t_1 = L \\sqrt{\\frac{m_2}{2qV}} - L \\sqrt{\\frac{m_1}{2qV}}$$\n提取公因式可得：\n$$\\Delta t = \\frac{L}{\\sqrt{2qV}} \\left( \\sqrt{m_2} - \\sqrt{m_1} \\right)$$\n首先，我们必须将所有给定的参数转换为国际单位制 (SI) 单位。\n质量以千道尔顿（$\\mathrm{kDa}$）为单位给出：\n$m_1 = 5 \\, \\mathrm{kDa} = 5000 \\, \\mathrm{Da}$\n$m_2 = 5.05 \\, \\mathrm{kDa} = 5050 \\, \\mathrm{Da}$\n使用换算关系 $1 \\, \\mathrm{Da} = 1.66053906660 \\times 10^{-27} \\, \\mathrm{kg}$：\n$$m_1 = 5000 \\times (1.66053906660 \\times 10^{-27} \\, \\mathrm{kg}) = 8.302695333 \\times 10^{-24} \\, \\mathrm{kg}$$\n$$m_2 = 5050 \\times (1.66053906660 \\times 10^{-27} \\, \\mathrm{kg}) = 8.38572228633 \\times 10^{-24} \\, \\mathrm{kg}$$\n其他参数为：\n飞行管长度：$L = 1.2 \\, \\mathrm{m}$\n加速电压：$V = 20 \\, \\mathrm{kV} = 20 \\times 10^3 \\, \\mathrm{V} = 2.0 \\times 10^4 \\, \\mathrm{V}$\n离子是单电荷的，所以它们的电荷 $q$ 是元电荷 $e$：\n$q = e = 1.602176634 \\times 10^{-19} \\, \\mathrm{C}$\n\n现在我们可以将这些值代入 $\\Delta t$ 的方程中。首先，我们计算项 $\\frac{L}{\\sqrt{2qV}}$ 的值：\n$$2qV = 2 \\times (1.602176634 \\times 10^{-19} \\, \\mathrm{C}) \\times (2.0 \\times 10^4 \\, \\mathrm{V}) = 6.408706536 \\times 10^{-15} \\, \\mathrm{J}$$\n$$\\frac{L}{\\sqrt{2qV}} = \\frac{1.2 \\, \\mathrm{m}}{\\sqrt{6.408706536 \\times 10^{-15} \\, \\mathrm{J}}} \\approx \\frac{1.2}{8.00543973 \\times 10^{-8}} \\, \\frac{\\mathrm{m}}{\\mathrm{J}^{1/2}} \\approx 1.49896488 \\times 10^7 \\, \\frac{\\mathrm{s}}{\\mathrm{kg}^{1/2}}$$\n接下来，我们计算项 $(\\sqrt{m_2} - \\sqrt{m_1})$：\n$$\\sqrt{m_1} = \\sqrt{8.302695333 \\times 10^{-24} \\, \\mathrm{kg}} \\approx 2.88143964 \\times 10^{-12} \\, \\mathrm{kg}^{1/2}$$\n$$\\sqrt{m_2} = \\sqrt{8.38572228633 \\times 10^{-24} \\, \\mathrm{kg}} \\approx 2.89581119 \\times 10^{-12} \\, \\mathrm{kg}^{1/2}$$\n$$\\sqrt{m_2} - \\sqrt{m_1} \\approx (2.89581119 - 2.88143964) \\times 10^{-12} \\, \\mathrm{kg}^{1/2} \\approx 1.437155 \\times 10^{-14} \\, \\mathrm{kg}^{1/2}$$\n现在，我们计算 $\\Delta t$：\n$$\\Delta t \\approx (1.49896488 \\times 10^7 \\, \\frac{\\mathrm{s}}{\\mathrm{kg}^{1/2}}) \\times (1.437155 \\times 10^{-14} \\, \\mathrm{kg}^{1/2})$$\n$$\\Delta t \\approx 2.154295 \\times 10^{-7} \\, \\mathrm{s}$$\n问题要求答案以纳秒（$1 \\, \\mathrm{ns} = 10^{-9} \\, \\mathrm{s}$）为单位，并四舍五入到四位有效数字。\n$$\\Delta t = (2.154295 \\times 10^{-7}) \\, \\mathrm{s} \\times \\frac{10^9 \\, \\mathrm{ns}}{1 \\, \\mathrm{s}} = 215.4295 \\, \\mathrm{ns}$$\n四舍五入到四位有效数字，我们得到：\n$$\\Delta t \\approx 215.4 \\, \\mathrm{ns}$$\n\n计算出的时间差 $\\Delta t$ 代表两种离子到达检测器的时间间隔。要使仪器能够区分这两个物种，这个时间间隔必须是可分辨的。这意味着质谱仪系统的整体时间分辨率必须显著小于 $215.4 \\, \\mathrm{ns}$，该分辨率由检测器响应时间、数字化仪采样率以及离子包本身的时间宽度决定。分辨这个 $\\Delta t$ 的能力与质量分辨能力 $R = m / \\Delta m$ 直接相关。在飞行时间质谱法 (TOF-MS) 中，分辨能力可以表示为 $R = t / (2 \\Delta t)$，其中 $\\Delta t$ 是对应于质量差 $\\Delta m$ 的峰之间的时间间隔。因此，测量这个时间差对于实现区分这两种细菌蛋白离子所需的质量分辨率至关重要。",
            "answer": "$$\\boxed{2.154 \\times 10^{2}}$$"
        },
        {
            "introduction": "从仪器获得的原始质谱图并非纯净的微生物蛋白质指纹，它往往混合了来自基质、培养基或实验室环境的各种“噪音”信号。解读这些复杂的谱图是微生物鉴定过程中的关键一步。这项练习将挑战您扮演一名分析侦探，根据质量、同位素分布和重复模式等特征，将真正的细菌蛋白质峰与常见的污染物峰区分开来，从而培养出在实际工作中至关重要的谱图解析能力 。",
            "id": "5230703",
            "problem": "一个实验室正在使用基质辅助激光解吸/电离飞行时间（MALDI-TOF）质谱法，通过点样基质α-氰基-4-羟基肉桂酸来鉴定单个菌落中的细菌。回顾以下基本事实：在MALDI中，离子主要为单电荷，因此其电荷约为$q = +e$。在通过电势差$V$加速后，获得的动能为$qV = \\tfrac{1}{2} m v^2$。对于固定的飞行路径，飞行时间$t$与$\\sqrt{m/q}$成正比，因此在单电荷谱图中，$m/z$的差异与质量$m$的差异成正比。给定离子的同位素变体之间相差约$1$道尔顿，因此表现为$m/z$上峰-峰间距约为$1$的峰包。重复的化学亚基会产生一系列峰，峰间距为该亚基的质量，而碱金属加合会使峰相对于质子化状态发生偏移，偏移量为加合物的质量。\n\n来自一个未知分离株的谱图显示了四个显著区域：\n\n- 区域A：在$m/z$ $3{,}000$–$12{,}000$之间有一组密集的窄峰，每个峰都有一个同位素峰包，峰间距约为$1$道尔顿。峰位不规则（在整个集合中没有恒定的间距）。\n- 区域B：在$m/z$ $600$到$2{,}000$范围内的一族峰，排列成近乎规则的系列，基本间距接近$189$道尔顿，并有旁系峰，偏移量分别约为$+23$和$+39$道尔顿。\n- 区域C：一个从$m/z$ $800$延伸到$4{,}000$的系列峰，在整个范围内具有近乎均匀的间隔，约为$44$道尔顿。\n- 区域D：两个强度非常高的峰，中心分别位于$m/z$ $15{,}100$和$m/z$ $15{,}900$附近。\n\n根据上述物理原理和典型的实验室经验，哪个选项最能区分此谱图中的常见污染物（基质簇、聚合物残留和培养基组分）与真实的微生物核糖体蛋白峰？\n\nA. 区域A是核糖体蛋白；区域B是α-氰基-4-羟基肉桂酸（单体约$189$道尔顿）的基质簇，带有钠和钾加合的旁系峰（约$+23$和$+39$道尔顿）；区域C是来自塑料制品或表面活性剂的聚乙二醇残留（重复单元约$44$道尔顿）；区域D反映了来自含血培养基的血红蛋白（亚基接近$15.1$和$15.9$千道尔顿）。\n\nB. 区域A是基质簇；区域B是核糖体蛋白；区域C是额外的核糖体蛋白；区域D反映了应包含在鉴定中的内在细菌血红蛋白。\n\nC. 区域A是聚合物残留；区域B是聚乙二醇；区域C是核糖体蛋白；区域D是外部校准物混合物，因此在未知物中是可接受的背景。\n\nD. 区域A是核糖体蛋白；区域B是一个聚合物系列（约$44$道尔顿重复）；区域C是基质簇（约$189$道尔顿重复）；区域D是校准峰，应始终存在于MALDI-TOF仪器中。\n\nE. 区域A是核糖体蛋白；区域B是脂多糖片段；区域C是基质簇，间距约为$44$道尔顿；区域D是血红素污染，解释了$15$–$16$千道尔顿的峰。",
            "solution": "### 问题验证\n\n**步骤 1：提取已知信息**\n\n问题陈述提供了以下信息：\n- **技术：** 基质辅助激光解吸/电离飞行时间（MALDI-TOF）质谱法。\n- **应用：** 细菌鉴定。\n- **基质：** α-氰基-4-羟基肉桂酸。\n- **离子物理学：**\n    - 离子主要为单电荷，因此电荷$q \\approx +e$。\n    - 获得的动能为$qV = \\tfrac{1}{2} m v^2$。\n    - 对于固定的飞行路径，飞行时间$t$与$\\sqrt{m/q}$成正比。\n    - 对于单电荷谱图，$m/z$的差异与质量$m$的差异成正比。\n- **谱图特征：**\n    - 同位素变体相差约$1$道尔顿，表现为$m/z$上峰-峰间距约为$1$的峰包。\n    - 重复的化学亚基产生一系列由亚基质量分隔的峰。\n    - 碱金属加合会使峰相对于质子化状态发生偏移，偏移量为加合物的质量。\n- **观察到的谱图区域：**\n    - **区域A：** 在$m/z$ $3{,}000$–$12{,}000$之间的一组密集的窄峰，峰位不规则，同位素峰包间距约为$1$道尔顿。\n    - **区域B：** 在$m/z$ $600$到$2{,}000$范围内的一族峰，排列成近乎规则的系列，基本间距接近$189$道尔顿，并有旁系峰，偏移量分别约为$+23$和$+39$道尔顿。\n    - **区域C：** 一个从$m/z$ $800$延伸到$4{,}000$的系列峰，具有近乎均匀的间隔，约为$44$道尔顿。\n    - **区域D：** 两个强度非常高的峰，中心分别位于$m/z$ $15{,}100$和$m/z$ $15{,}900$附近。\n\n**步骤 2：使用提取的已知信息进行验证**\n\n必须评估问题的科学合理性、客观性和问题的明确性。\n\n- **科学依据：** 该问题牢固地建立在MALDI-TOF质谱法及其在临床微生物学中应用的原理之上。\n    - 物理原理（$qV = \\frac{1}{2}mv^2$，$t \\propto \\sqrt{m/q}$）陈述正确。\n    - 对谱图特征（同位素峰包、聚合物系列、加合物）的描述是准确的。\n    - 指定基质α-氰基-4-羟基肉桂酸（$C_{10}H_7NO_3$）的质量为$189.17$ g/mol，与区域B中观察到的约$189$道尔顿的间距一致。\n    - 约$+23$道尔顿和约$+39$道尔顿的偏移量与钠加合（$Na$，原子质量约$22.99$ u）和钾加合（$K$，原子质量约$39.10$ u）一致，这些是常见的碱金属加合物。\n    - 区域C中约$44$道尔顿的间距是聚乙二醇（PEG）的经典特征，PEG是一种常见的实验室聚合物污染物，其重复单元为环氧乙烷（$-C_2H_4O-$），质量为$44.05$ Da。\n    - 区域D中的质量（约$15{,}100$ Da和约$15{,}900$ Da）与血红蛋白的α-和β-珠蛋白链（人α-珠蛋白：$15{,}126.4$ Da；β-珠蛋白：$15{,}867.2$ Da）非常匹配，这是从血琼脂上生长的细菌中已知的污染物。\n    - 区域A的描述（$m/z$ $3{,}000$–$12{,}000$范围内密集、不规则的峰）是用于细菌鉴定的丰富核糖体蛋白的典型“指纹图谱”。来自不同基因的蛋白质具有独特的质量，从而导致不规则的模式。\n\n- **问题的明确性和客观性：** 该问题对一个典型的质谱图进行了清晰、定量的描述。问题是明确的：根据所提供的物理原理和标准实验室知识，解释谱图并区分期望的生物信号与常见的伪影。语言客观且技术性强。\n\n- **验证结论：** 这个问题在科学上是合理的，问题明确，客观且完整。它准确地反映了一个真实的分析场景。没有发现任何缺陷。\n\n**结论：** 问题是 **有效的**。\n\n### 解题推导\n\n任务是根据质谱原理以及对微生物MALDI-TOF中常见分析物和污染物的了解，正确地为四个光谱区域（A、B、C和D）中观察到的信号指定化学身份。\n\n**光谱区域分析：**\n\n- **区域A（$m/z$ $3{,}000$–$12{,}000$）：** 该区域包含高密度的峰，间距不规则。每个峰都表现出$\\Delta m/z \\approx 1$的同位素峰包，这是含有许多碳原子的大分子的特征。这个质量范围和不规则的模式是微生物蛋白质指纹图谱的决定性特征，该图谱主要由各种核糖体蛋白和其他丰富的细胞蛋白组成。这些蛋白质不共享一个共同的重复亚基，因此间距不规则。该区域代表用于鉴定的真实微生物信号。\n\n- **区域B（$m/z$ $600$–$2{,}000$）：** 该区域显示出一系列规则的峰，间距约为$189$道尔顿。问题指出基质是α-氰基-4-羟基肉桂酸（HCCA），其分子量约为$189$道尔顿。因此，该系列代表基质簇，例如$[(HCCA)_n + H]^+$。偏移约$+23$和$+39$道尔顿的旁系峰对应于用钠离子（$Na^+$，质量约$23$ Da）或钾离子（$K^+$，质量约$39$ Da）替换质子（$H^+$，质量约$1$ Da），形成如$[(HCCA)_n + Na]^+$和$[(HCCA)_n + K]^+$的加合系列。这种与基质相关的信号是常见的低质量伪影。\n\n- **区域C（$m/z$ $800$–$4{,}000$）：** 该区域显示出一系列高度规则的峰，均匀间隔约为$44$道尔顿。这是聚乙二醇（PEG）明确无误的特征，PEG是一种聚合物，其重复单元为（$-CH_2CH_2O-$），质量约为$44$ Da。PEG是实验室中无处不在的污染物，通常从塑料耗材（如Eppendorf管）中浸出，或存在于洗涤剂和表面活性剂中。\n\n- **区域D（$m/z \\approx 15{,}100$ 和 $m/z \\approx 15{,}900$）：** 这两个强度高的高质量峰对应于约$15.1$ kDa和$15.9$ kDa的质量。这些质量与血红蛋白的α链（约$15.1$ kDa）和β链（约$15.9$ kDa）非常接近。当从血琼脂平板上挑取细菌菌落时，血红蛋白是临床微生物学实验室中一种常见且众所周知的污染物。对于大多数物种来说，这些峰不属于标准细菌蛋白质指纹图谱的一部分，被认为是来自生长培养基的伪影。\n\n**鉴定总结：**\n- **区域A：** 微生物核糖体蛋白（期望信号）。\n- **区域B：** 基质（HCCA）簇和加合物（污染物）。\n- **区域C：** 聚乙二醇（PEG）聚合物（污染物）。\n- **区域D：** 血红蛋白亚基（来自培养基的污染物）。\n\n###逐项分析\n\n- **选项A：** 此选项指定：\n    - 区域A为核糖体蛋白。**正确。**\n    - 区域B为α-氰基-4-羟基肉桂酸（约$189$ Da）的基质簇，带有钠（约$+23$ Da）和钾（约$+39$ Da）加合物。**正确。**\n    - 区域C为聚乙二醇残留（约$44$ Da重复）。**正确。**\n    - 区域D为来自含血培养基的血红蛋白（约$15.1$ kDa和$15.9$ kDa亚基）。**正确。**\n    此选项正确识别了所有区域，区分了真实信号与各种常见污染物。\n    **结论：正确。**\n\n- **选项B：** 此选项指定：\n    - 区域A为基质簇。**错误。** 基质簇在区域B。区域A的特征（高质量、不规则间距）与基质簇不符。\n    - 区域B为核糖体蛋白。**错误。** 核糖体蛋白在区域A。区域B的特征（低质量、规则间距）与蛋白质指纹图谱不符。\n    **结论：错误。**\n\n- **选项C：** 此选项指定：\n    - 区域A为聚合物残留。**错误。** 像PEG这样的聚合物残留具有规则的间距，而区域A是不规则的。\n    - 区域C为核糖体蛋白。**错误。** 区域C具有约$44$ Da的规则间距，且质量对于主要的蛋白质指纹图谱来说太低，后者是不规则且在更高质量区域（区域A）。\n    **结论：错误。**\n\n- **选项D：** 此选项指定：\n    - 区域B为重复单元约$44$道尔顿的聚合物系列。**错误。** 区域B的重复单元约$189$道尔顿。这错误地将区域B识别为PEG。\n    - 区域C为重复单元约$189$道尔顿的基质簇。**错误。** 区域C的重复单元约$44$道尔顿。这错误地将区域C识别为基质簇。该选项交换了B和C的身份。\n    - 区域D为应始终存在的校准峰。**错误。** 虽然使用校准物，但血红蛋白是一种特定的污染物，而不是通用的校准物。说它“应始终存在”是错误的。\n    **结论：错误。**\n\n- **选项E：** 此选项指定：\n    - 区域B为脂多糖片段。**错误。** 虽然在某些情况下是合理的，但$189$ Da的质量与基质单体完全匹配，并且加合物的存在使得基质簇的鉴定更为确定和简洁。\n    - 区域C为间距约$44$道尔顿的基质簇。**错误。** 基质是HCCA（约$189$ Da），因此它不能产生间距约$44$ Da的系列峰。\n    - 区域D为血红素污染。**错误/不精确。** 血红素是小的卟啉辅基（质量约$616$ Da）。观察到的峰在约$15-16$ kDa，对应于珠蛋白*蛋白质*，即血红蛋白，而不是血红素基团本身。\n    **结论：错误。**",
            "answer": "$$\\boxed{A}$$"
        },
        {
            "introduction": "为什么有时即使仪器校准良好，谱图上的峰依然与标准库不匹配？答案往往隐藏在样品制备的化学细节中。此项练习通过一个假设情景，探讨了离子化过程中的竞争性化学平衡——质子化与碱金属加合，揭示了样品中盐分的存在如何导致信号峰发生系统性偏移。通过这个实践，您将深刻理解为什么严格的样品脱盐处理对于获得准确、可重复的鉴定结果是不可或缺的 。",
            "id": "5230759",
            "problem": "一家临床实验室使用基质辅助激光解吸/电离飞行时间（MALDI-TOF）质谱法，通过将丰富的核糖体蛋白和管家蛋白的测量质荷比（$m/z$）图谱与参考库进行比较来鉴定微生物。在正离子模式下，待测蛋白或肽 $\\mathrm{M}$ 通常以质子化的 $[\\text{M+H}]^+$ 形式出现，或者以碱金属阳离子化的 $[\\text{M+Na}]^+$ 和 $[\\text{M+K}]^+$ 形式出现。基质是一种有机酸，在激光照射下充当质子给体；样品也可能携带来自培养基的残留钠盐和钾盐。假设两个 MALDI 点样的科学合理条件如下：\n\n- 点样 $1$（新鲜的酸性基质；脱盐的提取物）：有效自由质子浓度 $[\\text{H}^+] = 10^{-2}\\,\\mathrm{M}$；残留盐浓度 $[\\text{Na}^+] = 10^{-4}\\,\\mathrm{M}$ 和 $[\\text{K}^+] = 2\\times 10^{-5}\\,\\mathrm{M}$。\n- 点样 $2$（老化的、酸性较弱的基质；含盐的提取物）：有效自由质子浓度 $[\\text{H}^+] = 10^{-4}\\,\\mathrm{M}$；残留盐浓度 $[\\text{Na}^+] = 10^{-2}\\,\\mathrm{M}$ 和 $[\\text{K}^+] = 5\\times 10^{-3}\\,\\mathrm{M}$。\n\n对于羽辉条件下的一个代表性微生物蛋白 $\\mathrm{M}$，设其有效气相缔合（结合）常数分别为：形成 $[\\text{M+H}]^+$ 的 $K_H = 10^{4}\\,\\mathrm{M}^{-1}$，形成 $[\\text{M+Na}]^+$ 的 $K_{Na} = 10^{3}\\,\\mathrm{M}^{-1}$，以及形成 $[\\text{M+K}]^+$ 的 $K_{K} = 6\\times 10^{2}\\,\\mathrm{M}^{-1}$。在单电荷形式下，相对于中性 $\\mathrm{M}$ 的近似 $m/z$ 位移为：$\\mathrm{H}^+$ 为 $+1.007$，$\\mathrm{Na}^+$ 为 $+22.990$，$\\mathrm{K}^+$ 为 $+38.964$。\n\n利用基本的酸碱和结合平衡从第一性原理出发进行推理，选择最能预测每个点样中主要加合物以及对依赖于匹配质子化参考指纹图谱的微生物鉴定所产生的实际影响的陈述。\n\nA. 在点样 $1$ 中，$[\\text{M+H}]^+$ 占主导地位。在点样 $2$ 中，$[\\text{M+Na}]^+$ 和 $[\\text{M+K}]^+$ 变得显著，其中 $[\\text{M+Na}]^+$ 强于 $[\\text{M+K}]^+$；质谱图显示相对于质子化峰存在约 $+23$ 或 $+39$ 的系统性 $m/z$ 上移，从而降低了与质子化指纹图谱的库匹配度。\n\nB. 点样 $1$ 和点样 $2$ 均由 $[\\text{M+Na}]^+$ 主导，因为碱金属的结合本质上比质子化更强，因此即使在酸性、脱盐的条件下，峰也统一地向上移动了约 $+23$。\n\nC. 在点样 $1$ 中，由于 $\\mathrm{K}^+$ 的配位作用比 $\\mathrm{H}^+$ 更强，$[\\text{M+K}]^+$ 占主导地位。在点样 $2$ 中，基质酸性的增加抑制了 $[\\text{M+H}]^+$ 的形成；较重的加合物减少了峰重叠并改善了鉴定效果。\n\nD. 在点样 $1$ 中，$[\\text{M+H}]^+$ 占主导地位。在点样 $2$ 中，由于 $K_H$ 是最大的常数，$[\\text{M+H}]^+$ 仍然占主导地位；盐分主要增加总离子产率，而不影响鉴定准确性。",
            "solution": "必须首先验证问题陈述的科学合理性、一致性和客观性。\n\n### 第1步：提取已知条件\n题目提供了以下信息：\n-   **待测物**：一种微生物蛋白或肽，$\\mathrm{M}$。\n-   **观测到的物种**：质子化的 $[\\text{M+H}]^+$, 钠化的 $[\\text{M+Na}]^+$, 和钾化的 $[\\text{M+K}]^+$。\n-   **相对于中性 $\\mathrm{M}$ 的单电荷离子的质荷比（$m/z$）位移**：\n    -   $\\Delta m(\\mathrm{H}^+) = +1.007$\n    -   $\\Delta m(\\mathrm{Na}^+) = +22.990$\n    -   $\\Delta m(\\mathrm{K}^+) = +38.964$\n-   **有效气相缔合常数**：\n    -   $K_H = 10^{4}\\,\\mathrm{M}^{-1}$ 对于 $\\mathrm{M} + \\mathrm{H}^+ \\rightleftharpoons [\\text{M+H}]^+$\n    -   $K_{Na} = 10^{3}\\,\\mathrm{M}^{-1}$ 对于 $\\mathrm{M} + \\mathrm{Na}^+ \\rightleftharpoons [\\text{M+Na}]^+$\n    -   $K_{K} = 6 \\times 10^{2}\\,\\mathrm{M}^{-1}$ 对于 $\\mathrm{M} + \\mathrm{K}^+ \\rightleftharpoons [\\text{M+K}]^+$\n-   **点样1的条件**（新鲜、酸性、脱盐）：\n    -   $[\\text{H}^+]_1 = 10^{-2}\\,\\mathrm{M}$\n    -   $[\\text{Na}^+]_1 = 10^{-4}\\,\\mathrm{M}$\n    -   $[\\text{K}^+]_1 = 2 \\times 10^{-5}\\,\\mathrm{M}$\n-   **点样2的条件**（老化、酸性较弱、含盐）：\n    -   $[\\text{H}^+]_2 = 10^{-4}\\,\\mathrm{M}$\n    -   $[\\text{Na}^+]_2 = 10^{-2}\\,\\mathrm{M}$\n    -   $[\\text{K}^+]_2 = 5 \\times 10^{-3}\\,\\mathrm{M}$\n\n### 第2步：使用提取的已知条件进行验证\n该问题描述了竞争性结合平衡，这是化学中的一个标准概念，并应用于 MALDI-TOF 质谱法的特定且实际的应用背景中。\n-   **科学依据**：质子化和碱金属加合物的形成是 MALDI-TOF MS 中一个基本且有充分文献记载的现象。使用酸性基质作为质子源，生物样品中存在残留盐，以及这些盐对所得质谱图的影响，这些都是事实正确的，并且是 MALDI-TOF 实践的核心。给定的结合常数和浓度对于模拟高质量（脱盐）和低质量（含盐）样品制备之间的差异是合理的。质量位移对应于相应同位素的原子量。该问题牢固地植根于分析化学和实验室诊断学。\n-   **题目定义明确**：该问题提供了所有必要的定量信息（浓度和结合常数），以确定不同离子物种的相对丰度。问题陈述清晰，可以利用化学平衡原理从所提供的数据中推导出一个唯一且有意义的答案。\n-   **客观性**：问题以精确、定量且无偏见的科学语言陈述。没有主观因素。\n\n### 第3步：结论与行动\n问题陈述是有效的。这是一个在分析化学领域中定义明确、科学上合理的问题。我将继续进行解答。\n\n### 推导\n三种加合物 $[\\text{M+H}]^+$, $[\\text{M+Na}]^+$, 和 $[\\text{M+K}]^+$ 的形成是竞争性平衡过程。每种物质的浓度由平衡表达式给出：\n$$[\\text{M+H}^+] = K_H [\\text{M}] [\\text{H}^+]$$\n$$[\\text{M+Na}^+] = K_{Na} [\\text{M}] [\\text{Na}^+]$$\n$$[\\text{M+K}^+] = K_{K} [\\text{M}] [\\text{K}^+]$$\n质谱图中这些离子的相对丰度，对应于观测峰的强度，与其各自的浓度成正比。由于中性待测物浓度 $[\\mathrm{M}]$ 是一个公共因子，因此可以通过计算其结合常数与相应阳离子浓度的乘积 $K_X[\\mathrm{X}^+]$ 来比较每种加合物形成的相对倾向。\n\n我们为每种加合物定义一个倾向性项 $P_X$：\n$P_H = K_H [\\text{H}^+]$\n$P_{Na} = K_{Na} [\\text{Na}^+]$\n$P_K = K_K [\\text{K}^+]$\n\n具有最高倾向性值的加合物将是质谱图中的主导物种。\n\n**对点样1的分析：**\n使用点样1的浓度：\n-   $[\\text{H}^+]_1 = 10^{-2}\\,\\mathrm{M}$\n-   $[\\text{Na}^+]_1 = 10^{-4}\\,\\mathrm{M}$\n-   $[\\text{K}^+]_1 = 2 \\times 10^{-5}\\,\\mathrm{M}$\n\n倾向性为：\n$P_{H,1} = (10^{4}\\,\\mathrm{M}^{-1}) \\times (10^{-2}\\,\\mathrm{M}) = 100$\n$P_{Na,1} = (10^{3}\\,\\mathrm{M}^{-1}) \\times (10^{-4}\\,\\mathrm{M}) = 0.1$\n$P_{K,1} = (6 \\times 10^{2}\\,\\mathrm{M}^{-1}) \\times (2 \\times 10^{-5}\\,\\mathrm{M}) = 12 \\times 10^{-3} = 0.012$\n\n比较这些值：$P_{H,1} (100) \\gg P_{Na,1} (0.1)  P_{K,1} (0.012)$。\n在点样1中，质子化物质 $[\\text{M+H}]^+$ 的形成远优于碱金属加合物。因此，$[\\text{M+H}]^+$ 将是主峰。\n\n**对点样2的分析：**\n使用点样2的浓度：\n-   $[\\text{H}^+]_2 = 10^{-4}\\,\\mathrm{M}$\n-   $[\\text{Na}^+]_2 = 10^{-2}\\,\\mathrm{M}$\n-   $[\\text{K}^+]_2 = 5 \\times 10^{-3}\\,\\mathrm{M}$\n\n倾向性为：\n$P_{H,2} = (10^{4}\\,\\mathrm{M}^{-1}) \\times (10^{-4}\\,\\mathrm{M}) = 1$\n$P_{Na,2} = (10^{3}\\,\\mathrm{M}^{-1}) \\times (10^{-2}\\,\\mathrm{M}) = 10$\n$P_{K,2} = (6 \\times 10^{2}\\,\\mathrm{M}^{-1}) \\times (5 \\times 10^{-3}\\,\\mathrm{M}) = 30 \\times 10^{-1} = 3$\n\n比较这些值：$P_{Na,2} (10)  P_{K,2} (3)  P_{H,2} (1)$。\n在点样2中，钠化物质 $[\\text{M+Na}]^+$ 的形成最有利，其次是钾化物质 $[\\text{M+K}]^+$。两者都显著比质子化物质 $[\\text{M+H}]^+$ 更突出。\n\n**实际影响：**\n基于 MALDI-TOF 的微生物鉴定依赖于将实验峰图谱与参考库进行匹配。这些库是使用在最佳条件下（类似于点样1）获得的光谱建立的，其中峰对应于质子化蛋白（$[\\text{M+H}]^+$）。\n对于点样2，主要峰将对应于 $[\\text{M+Na}]^+$ 和 $[\\text{M+K}]^+$。\n这些加合物的 $m/z$ 值将相对于预期的质子化峰发生位移。\n从 $[\\text{M+H}]^+$ 到 $[\\text{M+Na}]^+$ 的位移是 $\\Delta m = m(\\mathrm{Na}^+) - m(\\mathrm{H}^+) = 22.990 - 1.007 = 21.983$。\n从 $[\\text{M+H}]^+$ 到 $[\\text{M+K}]^+$ 的位移是 $\\Delta m = m(\\mathrm{K}^+) - m(\\mathrm{H}^+) = 38.964 - 1.007 = 37.957$。\n对于给定的蛋白 $\\mathrm{M}$，质谱峰将出现在比预期质子化峰高约 $22$ 和 $38$ 个单位的 $m/z$ 值处。实验谱图（由盐加合物主导）与参考谱图（由质子化物质主导）之间的这种不匹配，会极大地降低模式匹配算法的得分，导致鉴定效果不佳或失败。\n\n### 逐项分析选项\n\n**A. 在点样 $1$ 中，$[\\text{M+H}]^+$ 占主导地位。在点样 $2$ 中，$[\\text{M+Na}]^+$ 和 $[\\text{M+K}]^+$ 变得显著，其中 $[\\text{M+Na}]^+$ 强于 $[\\text{M+K}]^+$；质谱图显示相对于质子化峰存在约 $+23$ 或 $+39$ 的系统性 $m/z$ 上移，从而降低了与质子化指纹图谱的库匹配度。**\n- 对点样1的预测：正确。我们的计算表明 $P_{H,1}$ 占主导地位。\n- 对点样2的预测：正确。我们的计算表明 $P_{Na,2}  P_{K,2}  P_{H,2}$，因此 $[\\text{M+Na}]^+$ 和 $[\\text{M+K}]^+$ 变得显著，且钠化加合物更强。\n- 影响：正确。质谱图将呈现出位移的峰。上移被表述为约 $+23$ 和 $+39$，这是对质量差异的合理且常见的简化。这种峰位移降低了库匹配度。\n这个选项与推导结果完全一致。**正确**。\n\n**B. 点样 $1$ 和点样 $2$ 均由 $[\\text{M+Na}]^+$ 主导，因为碱金属的结合本质上比质子化更强，因此即使在酸性、脱盐的条件下，峰也统一地向上移动了约 $+23$。**\n- 对点样1的预测：不正确。我们的分析表明，在点样1中 $[\\text{M+H}]^+$ 占主导地位。\n- 推理：不正确。“本质上更强”的结合前提是错误的；结合常数显示 $K_H  K_{Na}$。结果取决于常数和浓度两者。\n**不正确**。\n\n**C. 在点样 $1$ 中，由于 $\\mathrm{K}^+$ 的配位作用比 $\\mathrm{H}^+$ 更强，$[\\text{M+K}]^+$ 占主导地位。在点样 $2$ 中，基质酸性的增加抑制了 $[\\text{M+H}]^+$ 的形成；较重的加合物减少了峰重叠并改善了鉴定效果。**\n- 对点样1的预测：不正确。$[\\text{M+H}]^+$ 占主导地位。其推理也是错误的，因为 $K_H  K_K$。\n- 对点样2的预测：推理“酸性的增加……抑制了”与事实不符。点样2的酸性比点样1*弱*。降低酸性才会抑制 $[\\text{M+H}]^+$ 的形成。\n- 影响：不正确。单一待测物形成多种加合物会使谱图复杂化，并*降低*鉴定效果，而不是改善它。\n**不正确**。\n\n**D. 在点样 $1$ 中，$[\\text{M+H}]^+$ 占主导地位。在点样 $2$ 中，由于 $K_H$ 是最大的常数，$[\\text{M+H}]^+$ 仍然占主导地位；盐分主要增加总离子产率，而不影响鉴定准确性。**\n- 对点样1的预测：正确。\n- 对点样2的预测：不正确。我们的分析表明，在点样2中 $[\\text{M+Na}]^+$ 和 $[\\text{M+K}]^+$ 占主导地位。仅依赖 $K_H$ 是最大常数的推理是有缺陷的，因为它忽略了浓度的影响。\n- 影响：不正确。高盐浓度会引入与参考库不匹配的峰，从而极大地影响鉴定准确性。\n**不正确**。",
            "answer": "$$\\boxed{A}$$"
        }
    ]
}