{
    "hands_on_practices": [
        {
            "introduction": "理论的强大之处在于其能够转化为可计算的预测。本练习旨在弥合Gouy-Chapman-Stern（GCS）理论与实际计算之间的鸿沟。您将从第一性原理出发，推导出连接表面电荷与扩散层电势的关键非线性方程（Grahame方程），并实现一个数值求解器来计算表面电势。通过直接比较对称的$1:1$电解质和非对称的$2:1$电解质体系，本实践将清晰地揭示离子价态如何极大地增强界面的非线性静电响应，这是理解复杂地球化学环境中离子行为的核心。",
            "id": "4081874",
            "problem": "在水溶液中，带电的矿物-电解质界面通过 Gouy–Chapman–Stern (GCS) 框架进行建模，该框架将非线性的 Poisson–Boltzmann 扩散层与一个被视为电容器的紧凑 Stern 层耦合起来。从第一性原理出发，你必须为给定的表面电荷密度 $\\,\\sigma\\,$ 和体相电解质组成，计算表面电势 $\\,\\psi_0\\,$，计算对象包括 $\\,2\\!:\\!1\\,$ 型电解质和 $\\,1\\!:\\!1\\,$ 型电解质。此比较必须揭示 $\\,2\\!:\\!1\\,$ 型电解质相对于 $\\,1\\!:\\!1\\,$ 型电解质时增强的非线性效应。\n\n仅使用以下基础出发点：\n- 垂直于平面界面的一个维度上的泊松方程：$$\\frac{d^2 \\psi}{dx^2} \\,=\\, -\\frac{\\rho(\\psi)}{\\varepsilon \\varepsilon_0},$$ 其中 $\\,\\psi\\,$ 是静电势，$\\,\\rho(\\psi)\\,$ 是局部电荷密度，$\\,\\varepsilon\\,$ 是相对介电常数，$\\,\\varepsilon_0\\,$ 是真空介电常数。\n- 对于价态为 $\\,z_i\\,$、体相摩尔浓度为 $\\,c_{i,\\infty}\\,$ 的离子种类 $\\,i\\,$，其玻尔兹曼分布给出在电势 $\\,\\psi\\,$ 下的局部浓度为 $$c_i(\\psi) \\,=\\, c_{i,\\infty} \\exp\\!\\left(-\\frac{z_i e \\psi}{k_{\\mathrm{B}} T}\\right),$$ 其中 $\\,e\\,$ 是元电荷，$\\,k_{\\mathrm{B}}\\,$ 是玻尔兹曼常数，$\\,T\\,$ 是绝对温度。\n- 由离子浓度得出的电荷密度：$$\\rho(\\psi) \\,=\\, F \\sum_i z_i c_i(\\psi),$$ 其中 $\\,F = N_{\\mathrm{A}} e\\,$ 是法拉第常数，$\\,N_{\\mathrm{A}}\\,$ 是阿伏伽德罗常数。\n- 体相电中性：$$\\sum_i z_i c_{i,\\infty} \\,=\\, 0.$$\n- 平面界面的边界条件：当 $\\,x \\to \\infty\\,$ 时，$\\,\\psi \\to 0\\,$ 且 $\\,d\\psi/dx \\to 0\\,$；在扩散层起点（内亥姆霍兹平面），电场满足 $\\,\\sigma \\,=\\, -\\varepsilon \\varepsilon_0 \\left.\\frac{d\\psi}{dx}\\right|_{x=0^+}\\,$。Stern 层被建模为一个面电容为 $\\,C_{\\mathrm{S}}\\,$ 的电容器，产生的电势降为 $$\\psi_0 - \\psi_{\\mathrm{d}} \\,=\\, \\frac{\\sigma}{C_{\\mathrm{S}}},$$ 其中 $\\,\\psi_{\\mathrm{d}}\\,$ 是扩散层起点的电势。\n\n任务：\n1. 从上述出发，推导一个关于 $\\,\\psi_{\\mathrm{d}}\\,$ 的非线性标量方程，该方程是 $\\,\\sigma\\,$、$\\,T\\,$、$\\,\\varepsilon\\,$、$\\,\\varepsilon_0\\,$ 和体相组成 $\\,\\{z_i, c_{i,\\infty}\\}\\,$ 的函数。除了所述原理所蕴含的公式外，不要引入任何快捷公式。\n2. 实现一个鲁棒的数值求根程序来求解每种电解质的 $\\,\\psi_{\\mathrm{d}}\\,$，然后计算 $\\,\\psi_0 = \\psi_{\\mathrm{d}} + \\sigma/C_{\\mathrm{S}}.$\n3. 对于阳离子价态为 $\\,z_+ = +2\\,$、阴离子价态为 $\\,z_- = -1\\,$ 的 $\\,2\\!:\\!1\\,$ 型电解质，通过设置 $\\,c_{+,\\infty} = C\\,$ 和 $\\,c_{-,\\infty} = 2C\\,$ 来强制实现体相电中性，其中 $\\,C\\,$ 是给定的体相化学式浓度。对于 $\\,1\\!:\\!1\\,$ 型电解质，使用 $\\,z_+ = +1\\,$、$\\,z_- = -1\\,$，并设 $\\,c_{+,\\infty} = c_{-,\\infty} = C\\,$。\n4. 所有电势以伏特表示。所有输入浓度必须被视为单位为 $\\,\\mathrm{mol/L}\\,$ 的摩尔浓度，并在内部转换为 $\\,\\mathrm{mol/m^3}\\,$。介电常数使用无量纲的 $\\,\\varepsilon\\,$ 和单位为 $\\,\\mathrm{F/m}\\,$ 的 $\\,\\varepsilon_0\\,$。表面电荷密度 $\\,\\sigma\\,$ 的单位是 $\\,\\mathrm{C/m^2}\\,$，Stern 电容 $\\,C_{\\mathrm{S}}\\,$ 的单位是 $\\,\\mathrm{F/m^2}\\,$，$\\,T\\,$ 的单位是 $\\,\\mathrm{K}\\,$。\n5. 对于每个测试案例，输出三个浮点数：计算出的 $\\,2\\!:\\!1\\,$ 型电解质的 $\\,\\psi_0\\,$（单位：伏特），计算出的 $\\,1\\!:\\!1\\,$ 型电解质的 $\\,\\psi_0\\,$（单位：伏特），以及比率 $\\,r = \\left|\\psi_0^{(2\\!:\\!1)}\\right|/\\left|\\psi_0^{(1\\!:\\!1)}\\right|\\,$（无量纲）。\n\n使用的物理常数：\n- $\\,e = 1.602176634\\times 10^{-19}\\,\\mathrm{C}\\,$，\n- $\\,k_{\\mathrm{B}} = 1.380649\\times 10^{-23}\\,\\mathrm{J/K}\\,$，\n- $\\,N_{\\mathrm{A}} = 6.02214076\\times 10^{23}\\,\\mathrm{mol^{-1}}\\,$，\n- $\\,F = N_{\\mathrm{A}} e\\,$，\n- $\\,\\varepsilon_0 = 8.8541878128\\times 10^{-12}\\,\\mathrm{F/m}\\,$。\n\n测试套件（五个案例，涵盖典型范围，包括符号反转、低和高离子强度以及 Stern 层限制）：\n- 案例 A（中等离子强度，负电荷）：$\\,\\sigma = -0.05\\,\\mathrm{C/m^2}\\,$, $\\,C = 0.1\\,\\mathrm{mol/L}\\,$, $\\,T = 298\\,\\mathrm{K}\\,$, $\\,\\varepsilon = 78.5\\,$, $\\,C_{\\mathrm{S}} = 0.2\\,\\mathrm{F/m^2}\\,$。\n- 案例 B（低离子强度，负电荷）：$\\,\\sigma = -0.005\\,\\mathrm{C/m^2}\\,$, $\\,C = 0.001\\,\\mathrm{mol/L}\\,$, $\\,T = 298\\,\\mathrm{K}\\,$, $\\,\\varepsilon = 78.5\\,$, $\\,C_{\\mathrm{S}} = 0.2\\,\\mathrm{F/m^2}\\,$。\n- 案例 C（高离子强度，强负电荷，小 Stern 电容）：$\\,\\sigma = -0.2\\,\\mathrm{C/m^2}\\,$, $\\,C = 1.0\\,\\mathrm{mol/L}\\,$, $\\,T = 298\\,\\mathrm{K}\\,$, $\\,\\varepsilon = 78.5\\,$, $\\,C_{\\mathrm{S}} = 0.05\\,\\mathrm{F/m^2}\\,$。\n- 案例 D（中等离子强度，正电荷）：$\\,\\sigma = +0.05\\,\\mathrm{C/m^2}\\,$, $\\,C = 0.1\\,\\mathrm{mol/L}\\,$, $\\,T = 298\\,\\mathrm{K}\\,$, $\\,\\varepsilon = 78.5\\,$, $\\,C_{\\mathrm{S}} = 0.2\\,\\mathrm{F/m^2}\\,$。\n- 案例 E（中等离子强度，负电荷，大 Stern 电容）：$\\,\\sigma = -0.05\\,\\mathrm{C/m^2}\\,$, $\\,C = 0.1\\,\\mathrm{mol/L}\\,$, $\\,T = 298\\,\\mathrm{K}\\,$, $\\,\\varepsilon = 78.5\\,$, $\\,C_{\\mathrm{S}} = 1.0\\,\\mathrm{F/m^2}\\,$。\n\n最终输出格式：\n你的程序应该产生单行输出，包含一个用方括号括起来的逗号分隔列表的结果。该列表必须按\n$$\\left[\\psi_0^{(2\\!:\\!1)}\\!,\\,\\psi_0^{(1\\!:\\!1)}\\!,\\,r\\right]_{\\text{案例 A}},\\ \\left[\\psi_0^{(2\\!:\\!1)}\\!,\\,\\psi_0^{(1\\!:\\!1)}\\!,\\,r\\right]_{\\text{案例 B}},\\ \\ldots,\\ \\left[\\psi_0^{(2\\!:\\!1)}\\!,\\,\\psi_0^{(1\\!:\\!1)}\\!,\\,r\\right]_{\\text{案例 E}},$$\n的顺序包含 $\\,15\\,$ 个浮点数，并平展成一个单一列表\n$$\\left[\\psi_0^{(2\\!:\\!1)}\\!,\\,\\psi_0^{(1\\!:\\!1)}\\!,\\,r,\\,\\psi_0^{(2\\!:\\!1)}\\!,\\,\\psi_0^{(1\\!:\\!1)}\\!,\\,r,\\,\\ldots\\right].$$\n所有电势单位为伏特，比率 $\\,r\\,$ 是无量纲的。不应打印任何额外文本。",
            "solution": "该问题要求使用 Gouy-Chapman-Stern (GCS) 模型计算带电矿物-电解质界面的表面电势 $\\,\\psi_0\\,$。必须基于第一性原理对 $\\,2\\!:\\!1\\,$ 和 $\\,1\\!:\\!1\\,$ 型电解质进行计算。解决方案包括两个主要步骤：首先，推导扩散层电势的控制非线性方程；其次，对此方程进行数值求解以找到 $\\,\\psi_0\\,$。\n\n### 控制方程的推导\n\n该模型的基础在于将泊松方程与离子浓度的玻尔兹曼分布耦合起来。我们从一维泊松方程开始，它描述了静电势 $\\,\\psi(x)\\,$ 作为与界面距离 $\\,x\\,$ 的函数：\n$$\n\\frac{d^2 \\psi}{dx^2} = -\\frac{\\rho(\\psi)}{\\varepsilon \\varepsilon_0}\n$$\n这里，$\\,\\varepsilon\\,$ 是介质的相对介电常数，$\\,\\varepsilon_0\\,$ 是真空介电常数，$\\,\\rho(\\psi)\\,$ 是局部空间电荷密度。电荷密度由局部离子种类 $\\,i\\,$ 的浓度 $\\,c_i(\\psi)\\,$ 及其相应的价态 $\\,z_i\\,$ 决定：\n$$\n\\rho(\\psi) = F \\sum_i z_i c_i(\\psi)\n$$\n其中 $\\,F = N_{\\mathrm{A}} e\\,$ 是法拉第常数，它将摩尔浓度与电荷密度关联起来。局部离子浓度由玻尔兹曼分布给出，该分布将其与体相浓度 $\\,c_{i,\\infty}\\,$（其中 $\\,\\psi=0\\,$）联系起来：\n$$\nc_i(\\psi) = c_{i,\\infty} \\exp\\left(-\\frac{z_i e \\psi}{k_{\\mathrm{B}} T}\\right)\n$$\n其中 $\\,e\\,$ 是元电荷，$\\,k_{\\mathrm{B}}\\,$ 是玻尔兹曼常数，$\\,T\\,$ 是绝对温度。所有浓度 $\\,c_i\\,$ 必须采用国际单位制（$\\,\\mathrm{mol/m^3}\\,$）。\n\n将 $\\,\\rho(\\psi)\\,$ 和 $\\,c_i(\\psi)\\,$ 的表达式代入泊松方程，得到非线性的 Poisson-Boltzmann (PB) 方程：\n$$\n\\frac{d^2 \\psi}{dx^2} = -\\frac{F}{\\varepsilon \\varepsilon_0} \\sum_i z_i c_{i,\\infty} \\exp\\left(-\\frac{z_i e \\psi}{k_{\\mathrm{B}} T}\\right)\n$$\n\n为了求解这个二阶微分方程，我们使用恒等式 $\\,2 \\frac{d\\psi}{dx} \\frac{d^2\\psi}{dx^2} = \\frac{d}{dx}\\left(\\frac{d\\psi}{dx}\\right)^2\\,$ 进行第一次积分。将 PB 方程两边乘以 $\\,2 \\frac{d\\psi}{dx}\\,$ 并从体相溶液（$\\,x \\to \\infty\\,$）积分到位置 $\\,x\\,$，得到：\n$$\n\\int_{\\infty}^{x} \\frac{d}{dx'}\\left(\\frac{d\\psi}{dx'}\\right)^2 dx' = -\\frac{2F}{\\varepsilon \\varepsilon_0} \\int_{\\infty}^{x} \\sum_i z_i c_{i,\\infty} \\exp\\left(-\\frac{z_i e \\psi}{k_{\\mathrm{B}} T}\\right) \\frac{d\\psi}{dx'} dx'\n$$\n体相溶液中的边界条件是当 $\\,x \\to \\infty\\,$ 时，$\\,\\psi \\to 0\\,$ 且 $\\,d\\psi/dx \\to 0\\,$。应用这些条件，左侧的积分变为 $\\,\\left(\\frac{d\\psi}{dx}\\right)^2\\,$。右侧的积分可以对 $\\,\\psi\\,$（从 $\\,0\\,$ 到 $\\,\\psi\\,$）进行求值：\n$$\n\\left(\\frac{d\\psi}{dx}\\right)^2 = -\\frac{2F}{\\varepsilon \\varepsilon_0} \\sum_i z_i c_{i,\\infty} \\int_0^\\psi \\exp\\left(-\\frac{z_i e \\psi'}{k_{\\mathrm{B}} T}\\right) d\\psi'\n$$\n$$\n\\left(\\frac{d\\psi}{dx}\\right)^2 = -\\frac{2F}{\\varepsilon \\varepsilon_0} \\sum_i z_i c_{i,\\infty} \\left[ -\\frac{k_{\\mathrm{B}} T}{z_i e} \\exp\\left(-\\frac{z_i e \\psi'}{k_{\\mathrm{B}} T}\\right) \\right]_0^\\psi\n$$\n使用 $\\,R = N_{\\mathrm{A}} k_{\\mathrm{B}}\\,$ 和 $\\,F = N_{\\mathrm{A}} e\\,$，我们有 $\\,F k_{\\mathrm{B}} T / e = N_{\\mathrm{A}} e k_{\\mathrm{B}} T / e = N_{\\mathrm{A}} k_{\\mathrm{B}} T = R T\\,$。这可将表达式简化为：\n$$\n\\left(\\frac{d\\psi}{dx}\\right)^2 = \\frac{2RT}{\\varepsilon \\varepsilon_0} \\sum_i c_{i,\\infty} \\left[ \\exp\\left(-\\frac{z_i e \\psi}{k_{\\mathrm{B}} T}\\right) - 1 \\right]\n$$\n该方程将电场与扩散层中任意点的电势联系起来。现在我们应用 Stern 层外边界（扩散层起点，记为 $\\,x=0^+\\,$）的边界条件。在该平面上，电势为 $\\,\\psi_{\\mathrm{d}}\\,$（扩散层电势），电场与矿物表面的表面电荷密度 $\\,\\sigma\\,$ 平衡：\n$$\n\\sigma = -\\varepsilon \\varepsilon_0 \\left.\\frac{d\\psi}{dx}\\right|_{x=0^+}\n$$\n对积分后的 PB 方程取平方根，并在 $\\,\\psi=\\psi_{\\mathrm{d}}\\,$ 处求值：\n$$\n\\left.\\frac{d\\psi}{dx}\\right|_{x=0^+} = -\\text{sgn}(\\psi_{\\mathrm{d}}) \\sqrt{\\frac{2RT}{\\varepsilon \\varepsilon_0} \\sum_i c_{i,\\infty} \\left[ \\exp\\left(-\\frac{z_i e \\psi_{\\mathrm{d}}}{k_{\\mathrm{B}} T}\\right) - 1 \\right]}\n$$\n符号的选择使得电势从 $\\,\\psi_{\\mathrm{d}}\\,$ 单调衰减到零。正的 $\\,\\psi_{\\mathrm{d}}\\,$ 需要负的电场，反之亦然。将此代入 $\\,\\sigma\\,$ 的边界条件，得到 Grahame 方程，该方程将表面电荷密度与扩散层电势联系起来：\n$$\n\\sigma = \\text{sgn}(\\psi_{\\mathrm{d}}) \\sqrt{2RT\\varepsilon \\varepsilon_0 \\sum_i c_{i,\\infty} \\left[ \\exp\\left(-\\frac{z_i e \\psi_{\\mathrm{d}}}{k_{\\mathrm{B}} T}\\right) - 1 \\right]}\n$$\n由于 $\\,\\text{sgn}(\\sigma) = \\text{sgn}(\\psi_{\\mathrm{d}})\\,$（正表面电荷引起正电势），我们可以将两边平方，得到需求解 $\\,\\psi_{\\mathrm{d}}\\,$ 的方程：\n$$\n\\sigma^2 = 2RT\\varepsilon \\varepsilon_0 \\sum_i c_{i,\\infty} \\left[ \\exp\\left(-\\frac{z_i e \\psi_{\\mathrm{d}}}{k_{\\mathrm{B}} T}\\right) - 1 \\right]\n$$\n\n### 特定电解质的公式\n\n对于对称的 **$\\,1\\!:\\!1\\,$ 型电解质**：$\\,z_+=+1\\,$, $\\,z_-=-1\\,$，且 $\\,c_{+,\\infty}=c_{-,\\infty}=C\\,$。求和项变为：\n$$\n\\sum_{1:1} = C \\left[ \\exp\\left(-\\frac{e \\psi_{\\mathrm{d}}}{k_{\\mathrm{B}} T}\\right) - 1 \\right] + C \\left[ \\exp\\left(+\\frac{e \\psi_{\\mathrm{d}}}{k_{\\mathrm{B}} T}\\right) - 1 \\right] = 2C \\left[ \\cosh\\left(\\frac{e \\psi_{\\mathrm{d}}}{k_{\\mathrm{B}} T}\\right) - 1 \\right]\n$$\n对于非对称的 **$\\,2\\!:\\!1\\,$ 型电解质**：$\\,z_+=+2\\,$, $\\,z_-=-1\\,$，体相电中性要求 $\\,c_{+,\\infty}=C\\,$, $\\,c_{-,\\infty}=2C\\,$。求和项为：\n$$\n\\sum_{2:1} = C \\left[ \\exp\\left(-\\frac{2e \\psi_{\\mathrm{d}}}{k_{\\mathrm{B}} T}\\right) - 1 \\right] + 2C \\left[ \\exp\\left(+\\frac{e \\psi_{\\mathrm{d}}}{k_{\\mathrm{B}} T}\\right) - 1 \\right] = C \\left[ \\exp\\left(-\\frac{2e \\psi_{\\mathrm{d}}}{k_{\\mathrm{B}} T}\\right) + 2\\exp\\left(\\frac{e \\psi_{\\mathrm{d}}}{k_{\\mathrm{B}} T}\\right) - 3 \\right]\n$$\n\n### 数值算法\n\n核心任务是为每种电解质类型和每组参数求解关于 $\\,\\psi_{\\mathrm{d}}\\,$ 的非线性标量方程。\n\n1.  **定义求根函数**：我们为数值求解器定义一个函数 $\\,f(\\psi_{\\mathrm{d}}) = 0\\,$：\n    $$\n    f(\\psi_{\\mathrm{d}}) = 2RT\\varepsilon \\varepsilon_0 \\sum_i c_{i,\\infty} \\left[ \\exp\\left(-\\frac{z_i e \\psi_{\\mathrm{d}}}{k_{\\mathrm{B}} T}\\right) - 1 \\right] - \\sigma^2 = 0\n    $$\n\n2.  **数值方法**：一个鲁棒的求根算法，例如 Brent-Dekker 方法 (`brentq`)，是理想的选择。此方法需要一个区间 $\\,[a, b]\\,$，使得 $\\,f(a)\\,$ 和 $\\,f(b)\\,$ 符号相反。\n    - 由于 $\\,\\text{sgn}(\\psi_{\\mathrm{d}}) = \\text{sgn}(\\sigma)\\,$，如果 $\\,\\sigma > 0\\,$，我们在正域（例如 $\\,(0, 2]\\,$ V）中寻找根。如果 $\\,\\sigma  0\\,$，我们在负域（例如 $\\,[-2, 0)\\,$ V）中寻找根。\n    - 当 $\\,\\psi_{\\mathrm{d}} \\to 0\\,$ 时，$\\,f(\\psi_{\\mathrm{d}}) \\to -\\sigma^2  0\\,$。对于 $\\,|\\psi_{\\mathrm{d}}| > 0\\,$，指数项增长，使得 $\\,f(\\psi_{\\mathrm{d}})\\,$ 随 $\\,|\\psi_{\\mathrm{d}}|\\,$ 单调增加。为区间选择一个合适的上界可以确保 $\\,f(\\psi_{\\mathrm{d}})\\,$ 变为正值，从而保证在区间内有唯一的根。对于 $\\,\\sigma=0\\,$ 的情况，解是平凡的 $\\,\\psi_{\\mathrm{d}} = 0\\,$。\n\n3.  **单位转换**：输入浓度 $\\,C\\,$ 的单位是 $\\,\\mathrm{mol/L}\\,$，必须通过乘以 $\\,1000\\,$ 转换为 $\\,\\mathrm{mol/m^3}\\,$。所有其他参数都已给定或转换为国际单位制基本单位。\n\n4.  **计算表面电势 $\\,\\psi_0\\,$**：在数值确定 $\\,\\psi_{\\mathrm{d}}\\,$ 后，通过加上 Stern 层上的电势降来计算表面总电势 $\\,\\psi_0\\,$，Stern 层被建模为一个简单的电容器：\n    $$\n    \\psi_0 = \\psi_{\\mathrm{d}} + \\frac{\\sigma}{C_{\\mathrm{S}}}\n    $$\n    其中 $\\,C_{\\mathrm{S}}\\,$ 是 Stern 层电容。\n\n对每个测试案例和两种电解质组成（$\\,1\\!:\\!1\\,$ 和 $\\,2\\!:\\!1\\,$）实施此程序，以计算所需的 $\\,\\psi_0\\,$ 值和比率 $\\,r = \\left|\\psi_0^{(2\\!:\\!1)}\\right|/\\left|\\psi_0^{(1\\!:\\!1)}\\right|\\,$。",
            "answer": "```python\nimport numpy as np\nfrom scipy.optimize import root_scalar\n\ndef solve():\n    \"\"\"\n    Solves the Gouy-Chapman-Stern model for specified test cases.\n    \"\"\"\n    \n    # Physical constants in SI units\n    E_CHARGE = 1.602176634e-19  # Elementary charge (C)\n    K_B = 1.380649e-23          # Boltzmann constant (J/K)\n    N_A = 6.02214076e+23        # Avogadro's number (mol^-1)\n    EPS_0 = 8.8541878128e-12    # Vacuum permittivity (F/m)\n    R = N_A * K_B               # Ideal gas constant (J/(mol*K))\n\n    test_cases = [\n        # Case A (moderate ionic strength, negative charge)\n        {'sigma': -0.05, 'C_L': 0.1, 'T': 298.0, 'eps_r': 78.5, 'C_S': 0.2},\n        # Case B (low ionic strength, negative charge)\n        {'sigma': -0.005, 'C_L': 0.001, 'T': 298.0, 'eps_r': 78.5, 'C_S': 0.2},\n        # Case C (high ionic strength, strong negative charge, small Stern capacitance)\n        {'sigma': -0.2, 'C_L': 1.0, 'T': 298.0, 'eps_r': 78.5, 'C_S': 0.05},\n        # Case D (moderate ionic strength, positive charge)\n        {'sigma': 0.05, 'C_L': 0.1, 'T': 298.0, 'eps_r': 78.5, 'C_S': 0.2},\n        # Case E (moderate ionic strength, negative charge, large Stern capacitance)\n        {'sigma': -0.05, 'C_L': 0.1, 'T': 298.0, 'eps_r': 78.5, 'C_S': 1.0},\n    ]\n\n    electrolytes = {\n        '2:1': {'valences': np.array([2, -1]), 'conc_factors': np.array([1, 2])},\n        '1:1': {'valences': np.array([1, -1]), 'conc_factors': np.array([1, 1])},\n    }\n\n    def calculate_psi0(sigma, C_L, T, eps_r, C_S, valences, conc_factors):\n        \"\"\"\n        Calculates the surface potential psi_0 for a given set of parameters.\n        \"\"\"\n        # Trivial case\n        if sigma == 0.0:\n            return 0.0\n\n        # Convert concentration from mol/L to mol/m^3\n        C_m3 = C_L * 1000.0\n        c_inf = C_m3 * conc_factors # mol/m^3\n\n        # Thermal energy term\n        beta = E_CHARGE / (K_B * T)\n        \n        # Prefactor for the Grahame equation\n        prefactor = 2.0 * R * T * eps_r * EPS_0\n\n        def f_psi_d(psi_d):\n            \"\"\"Target function for root finding: f(psi_d) = 0.\"\"\"\n            exp_term = np.exp(-valences * beta * psi_d)\n            sum_term = np.sum(c_inf * (exp_term - 1.0))\n            return prefactor * sum_term - sigma**2\n\n        # Set search bracket based on the sign of sigma\n        # sgn(psi_d) must equal sgn(sigma)\n        bracket = None\n        if sigma > 0:\n            bracket = [1e-9, 5.0]  # Search for a positive root\n        else: # sigma  0\n            bracket = [-5.0, -1e-9] # Search for a negative root\n\n        # Solve for psi_d using a robust root-finding algorithm\n        sol = root_scalar(f_psi_d, bracket=bracket, method='brentq')\n        psi_d = sol.root\n\n        # Calculate psi_0 using the Stern layer capacitor model\n        psi_0 = psi_d + sigma / C_S\n        \n        return psi_0\n\n    results = []\n    for case in test_cases:\n        # Calculate psi_0 for the 2:1 electrolyte\n        psi0_21 = calculate_psi0(\n            case['sigma'], case['C_L'], case['T'], case['eps_r'], case['C_S'],\n            electrolytes['2:1']['valences'], electrolytes['2:1']['conc_factors']\n        )\n        \n        # Calculate psi_0 for the 1:1 electrolyte\n        psi0_11 = calculate_psi0(\n            case['sigma'], case['C_L'], case['T'], case['eps_r'], case['C_S'],\n            electrolytes['1:1']['valences'], electrolytes['1:1']['conc_factors']\n        )\n        \n        # Calculate the ratio r\n        if abs(psi0_11) > 1e-12: # Avoid division by zero\n            r = abs(psi0_21) / abs(psi0_11)\n        else:\n            r = np.inf if abs(psi0_21) > 1e-12 else 1.0\n            \n        results.extend([psi0_21, psi0_11, r])\n\n    # Format the output as a single comma-separated list in brackets\n    print(f\"[{','.join(map(str, results))}]\")\n\nsolve()\n```"
        },
        {
            "introduction": "任何物理模型都有其适用边界，理解这些边界与掌握模型本身同样重要。在建立了求解GCS模型的能力之后，本练习将引导您探索其根本性局限。标准的GCS模型是一种平均场理论，它忽略了离子间的静电关联。本练习探讨了在高表面电荷和多价阳离子存在的条件下，离子间的强耦合效应会变得至关重要，甚至可能引发平均场理论无法预测的“电荷反转”（charge inversion）现象。通过评估这一现象，您将学会批判性地审视模型假设，并认识到何时需要引入更高级的理论（如强耦合理论或考虑特定吸附的扩展模型）。",
            "id": "4081826",
            "problem": "在温度为 $298\\ \\mathrm{K}$ 的水中，一个平面硅酸盐表面带有一层均匀的负表面电荷密度 $\\sigma_0=-0.10\\ \\mathrm{C}\\,\\mathrm{m}^{-2}$。该界面通过 Gouy-Chapman-Stern (GCS) 框架进行建模：一个紧邻表面的紧密 Stern 层（具有线性电容的离子排斥区）与一个由 Poisson-Boltzmann (PB) 方程控制的扩散层串联。考虑处于体平衡状态的两种电解质：(i) 体浓度为 $100\\ \\mathrm{mM}$ 的 $1{:}1$ 型电解质；(ii) 体浓度为 $10\\ \\mathrm{mM}$ 的含 $\\mathrm{CaCl}_2$ 的 $2{:}1$ 型电解质。假设在 $298\\ \\mathrm{K}$ 时，水的相对介电常数 $\\varepsilon_r=78.5$，Bjerrum 长度为 $\\ell_B=e^2/(4\\pi \\varepsilon_0 \\varepsilon_r k_B T)\\approx 0.714\\ \\mathrm{nm}$，其中 $e$ 是元电荷，$\\varepsilon_0$ 是真空介电常数，$k_B$ 是 Boltzmann 常数，$T$ 是绝对温度。设 $z$ 表示反离子价态，对于 $1{:}1$ 型电解质，$z=1$；对于 $\\mathrm{Ca}^{2+}$ 情况，$z=2$。\n\n仅从 (a) 平面界面的高斯定律，(b) 静电势中离子的玻尔兹曼分布，以及 (c) Bjerrum 长度作为两个单位电荷相互作用能等于热能的长度尺度的定义出发，论证表面附近的离子-离子关联强度，并判断是否预期会发生由关联引起的电荷反转（也称为过充电）。具体而言，通过比较中和表面所需的反离子之间的典型横向间距与该间距下的静电相互作用强度，估算一个合适的强耦合度量。然后评估如上定义的、且不包含任何额外关联或化学络合物理的标准 GCS 模型是否能够产生电荷反转。\n\n选择所有正确的陈述：\n\nA. 对于 $z=2$ 和 $\\sigma_0=-0.10\\ \\mathrm{C}\\,\\mathrm{m}^{-2}$，表面附近相邻反离子间的估算静电耦合很强（无量纲耦合参数 $\\gtrsim \\mathcal{O}(10)$），因此离子-离子关联是重要的，且在这些条件下原则上可以驱动关联引起的电荷反转。\n\nB. 在具有线性 Stern 层的标准 PB 扩散层中（即不含任何关联校正或特定化学吸附的基准 GCS 模型），电荷反转不会发生；扩散层电荷补偿有效表面电荷，而不会过度屏蔽它。\n\nC. 在基准 GCS 模型中，仅仅增加 Stern 层的电容，而不考虑关联或特定吸附，就可以反转远场电势的符号，从而产生电荷反转。\n\nD. 如果将 Stern 层扩展，通过质量作用平衡（特定吸附）包含 $\\mathrm{Ca}^{2+}$ 的内层络合，那么在扩展的 GCS 框架内可以重现表观过充电甚至 zeta 电势反转；然而，这构成了对基准模型的修改。\n\nE. 在 PB 理论中，足够高的离子强度（小的 Debye 长度）本身就足以产生电荷反转，即使对于单价离子也是如此，因为更强的屏蔽必然导致过度屏蔽。\n\n选择所有适用的选项。",
            "solution": "问题陈述已经过验证，被认为是科学上合理、提法恰当且足够完整可以求解的。该问题要求基于 Gouy-Chapman-Stern (GCS) 模型和强耦合静电学原理，对关于带电平面界面处电荷反转的几个陈述进行评估。\n\n如问题中所定义的，标准 GCS 模型由一个紧密 Stern 层和一个由平均场 Poisson-Boltzmann (PB) 理论描述的扩散层组成。对于从扩散层起点开始的距离 $x$ 的函数——静电势 $\\psi$ 的一维 PB 方程由下式给出：\n$$ \\frac{d^2\\psi}{dx^2} = -\\frac{\\rho(x)}{\\varepsilon_0 \\varepsilon_r} $$\n其中 $\\varepsilon_0$ 是真空介电常数，$\\varepsilon_r$ 是溶剂的相对介电常数，$\\rho(x)$ 是离子的局域电荷密度。在 PB 理论中，$\\rho(x)$ 通过玻尔兹曼分布与局域电势 $\\psi(x)$ 相关。对于包含价态为 $z_i$、体浓度为 $c_{\\infty,i}$ 的离子种类 $i$ 的电解质，其数密度为 $c_i(x) = c_{\\infty,i} \\exp(-z_i e \\psi(x) / (k_B T))$，其中 $e$ 是元电荷，$k_B$ 是 Boltzmann 常数，$T$ 是温度。因此，电荷密度为 $\\rho(x) = \\sum_i z_i e c_i(x)$。\n\n对于单个平面表面的一维 PB 方程，一个关键特征是电势分布 $\\psi(x)$ 总是单调的。对于带负电的表面（$\\sigma_0  0$），表面电势 $\\psi_0$ 和扩散层起点处的电势 $\\psi_d$ 将为负值。然后，电势 $\\psi(x)$ 将从 $\\psi_d$ 单调衰减至 $0$（当 $x \\to \\infty$ 时）。电荷反转或过充电定义为电势符号的反转，这意味着 $\\psi(x)$ 必须是非单调的（例如，从负值开始，变为正值，然后衰减到零）。这在 PB 框架内是数学上不允许的。扩散层中的总电荷 $\\sigma_d$ 将始终与 $\\psi_d$ 的符号相反，并且将精确补偿 Stern/扩散层边界处的有效电荷，其绝对值永远不会超过有效电荷。这是平均场理论的一个基本限制。\n\n在此基础上，我们来评估每个选项。\n\n**A. 对于 $z=2$ 和 $\\sigma_0=-0.10\\ \\mathrm{C}\\,\\mathrm{m}^{-2}$，表面附近相邻反离子间的估算静电耦合很强（无量纲耦合参数 $\\gtrsim \\mathcal{O}(10)$），因此离子-离子关联是重要的，且在这些条件下原则上可以驱动关联引起的电荷反转。**\n\n该陈述涉及 PB 理论失效的范畴。当离散离子间的静电关联变得显著时，PB 理论就会失效，这种情况被称为强耦合。这通常发生在存在多价离子（$|z| \\ge 2$）和/或高电荷表面的情况下。\n\n问题要求估算一个耦合参数。我们按照说明操作：比较反离子的典型横向间距与其相互作用能。\n1. 中和表面电荷 $\\sigma_0$ 所需的单位面积反离子数量 $n_A$ 由 $n_A (ze) = |\\sigma_0|$ 给出。\n2. 每个离子的平均面积为 $A_{ion} = 1/n_A = ze/|\\sigma_0|$。\n3. 典型的横向间距为 $d_{lat} \\approx \\sqrt{A_{ion}} = \\sqrt{ze/|\\sigma_0|}$。\n当 $z=2$，$|\\sigma_0|=0.10\\ \\mathrm{C}\\,\\mathrm{m}^{-2}$ 且 $e \\approx 1.602 \\times 10^{-19}\\ \\mathrm{C}$ 时：\n$$ d_{lat} \\approx \\sqrt{\\frac{2 \\times 1.602 \\times 10^{-19}\\ \\mathrm{C}}{0.10\\ \\mathrm{C}\\,\\mathrm{m}^{-2}}} \\approx 1.79 \\times 10^{-9}\\ \\mathrm{m} = 1.79\\ \\mathrm{nm} $$\n4. 在此间距下，两个此类反离子间的静电相互作用能为 $U_{int} = (ze)^2 / (4\\pi \\varepsilon_0 \\varepsilon_r d_{lat})$。\n5. 无量纲耦合参数是该能量与热能的比值，$\\Gamma = U_{int}/(k_B T)$。使用 Bjerrum 长度 $\\ell_B = e^2 / (4\\pi \\varepsilon_0 \\varepsilon_r k_B T) \\approx 0.714\\ \\mathrm{nm}$：\n$$ \\Gamma = \\frac{z^2 \\ell_B}{d_{lat}} = \\frac{2^2 \\times (0.714\\ \\mathrm{nm})}{1.79\\ \\mathrm{nm}} \\approx 1.59 $$\n这个值表明关联是不可忽略的，但它与 $\\gtrsim \\mathcal{O}(10)$ 的说法不符。\n\n然而，文献中用于该系统的更标准的无量纲耦合参数是 $\\Xi = 2\\pi z^2 \\ell_B |\\sigma_0|/e$。计算该值：\n$$ \\Xi = \\frac{2\\pi \\times 2^2 \\times (0.714 \\times 10^{-9}\\ \\mathrm{m}) \\times (0.10\\ \\mathrm{C}\\,\\mathrm{m}^{-2})}{1.602 \\times 10^{-19}\\ \\mathrm{C}} \\approx 11.16 $$\n这个值确实在 10 的数量级。当 $\\Xi \\gg 1$ 时，系统处于强耦合区域。在该区域中，反离子在表面附近形成强关联液体，其中离子-离子排斥占主导地位。这可能导致堆积排列，从而过度补偿原始表面电荷，引起电荷反转。因此，对于给定的条件，该陈述的物理结论是正确的，并且数值估算与耦合参数 $\\Xi$ 的标准定义相符。关联确实是重要的，并且可以驱动电荷反转。\n\n结论：**正确**。\n\n**B. 在具有线性 Stern 层的标准 PB 扩散层中（即不含任何关联校正或特定化学吸附的基准 GCS 模型），电荷反转不会发生；扩散层电荷补偿有效表面电荷，而不会过度屏蔽它。**\n\n正如引言中所述，该陈述是一维 Poisson-Boltzmann 方程数学结构的直接结果。电势分布已被证明是单调的。对于带负电的表面，电势从负值衰减到零，符号不变。因此，需要一个改变符号的非单调电势的电荷反转是不可能的。GCS 模型由于对扩散层使用 PB 理论，也继承了这一基本限制。扩散层精确提供中和所需的电荷，不多不少。\n\n结论：**正确**。\n\n**C. 在基准 GCS 模型中，仅仅增加 Stern 层的电容，而不考虑关联或特定吸附，就可以反转远场电势的符号，从而产生电荷反转。**\n\n在基准 GCS 模型中，我们有电中性条件 $\\sigma_0 + \\sigma_d = 0$（假设 Stern 平面中没有特定吸附，即 $\\sigma_S=0$）。这固定了扩散层电荷 $\\sigma_d = -\\sigma_0$。扩散层起点处的电势 $\\psi_d$ 由 $\\sigma_d$ 通过 Grahame 方程唯一确定。Stern 层电容 $C_S$ 将表面电荷 $\\sigma_0$ 与跨越 Stern 层的电势降联系起来：$\\psi_0 - \\psi_d = \\sigma_0 / C_S$。改变 $C_S$ 只会改变表面电势 $\\psi_0$。它对 $\\psi_d$ 或扩散区域（$x > d_{\\text{Stern}}$）中的电势分布没有影响。由于扩散层中的电势分布由 PB 方程控制并从固定的 $\\psi_d$ 开始，并且由于 PB 理论不允许电荷反转，因此改变 $C_S$ 不能诱发它。\n\n结论：**不正确**。\n\n**D. 如果将 Stern 层扩展，通过质量作用平衡（特定吸附）包含 $\\mathrm{Ca}^{2+}$ 的内层络合，那么在扩展的 GCS 框架内可以重现表观过充电甚至 zeta 电势反转；然而，这构成了对基准模型的修改。**\n\n特定吸附是指离子与表面发生强的、短程的化学键合，形成内层或外层络合物。这种机制不同于 PB 理论所描述的扩散积累。如果像 $\\mathrm{Ca}^{2+}$ 这样的多价反离子特定吸附到负电荷表面（$\\sigma_0  0$），它们会在 Stern 平面内增加一个正电荷层 $\\sigma_S > 0$。物理上，这个吸附电荷的量值可能超过表面电荷，即 $\\sigma_S > |\\sigma_0|$。表面加上 Stern 层的总电荷变为正值：$\\sigma_{eff} = \\sigma_0 + \\sigma_S > 0$。为了维持整体电中性，扩散层必须形成一个净负电荷（$\\sigma_d = -\\sigma_{eff}  0$）。这意味着扩散层起点处的电势 $\\psi_d$ 必须为正。由于 zeta 电势与 $\\psi_d$ 密切相关，它的符号也将从负变为正。这种现象被称为“表观”过充电，因为它是由化学键合而非静电关联驱动的。正如问题正确指出的，通过质量作用定律引入特定吸附是对仅定义了离子排斥层的“基准”GCS 模型的扩展。\n\n结论：**正确**。\n\n**E. 在 PB 理论中，足够高的离子强度（小的 Debye 长度）本身就足以产生电荷反转，即使对于单价离子也是如此，因为更强的屏蔽必然导致过度屏蔽。**\n\n这个陈述是不正确的。正如对选项 B 的讨论，PB 理论根本无法在任何参数集（离子强度、价态等）下产生电荷反转。增加离子强度会减小 Debye 长度 $\\kappa^{-1}$。这会导致电势更快速但仍然是单调的衰减。在 PB 理论的背景下，“更强的屏蔽”意味着电场在更短的距离内被中和；它绝对不意味着“过度屏蔽”（电荷反转）。该陈述错误地将这两个不同的概念等同起来。\n\n结论：**不正确**。",
            "answer": "$$\\boxed{ABD}$$"
        },
        {
            "introduction": "将理论模型应用于真实的地球化学系统时，必须审慎处理非理想性。例如，地下盐水等高盐度流体的离子浓度极高，远超理想溶液的范畴。本练习聚焦于在高盐度环境中正确应用GCS理论的一个关键细节：如何定义德拜长度（Debye length）中的离子强度。通过辨析使用浓度与使用活度的不同后果，本实践旨在纠正一个常见的理论误区，并强调在静电屏蔽计算中必须回归其物理本源——即电荷的实际数量密度，而非其热力学有效性。这对于准确模拟真实地质流体中的界面过程至关重要。",
            "id": "4081855",
            "problem": "一个平面碳酸盐界面在温度 $T=298\\,\\mathrm{K}$ 的高盐度盐水中，使用Gouy–Chapman–Stern框架进行建模。主体电解质是氯化钠和氯化钙的混合物，其质量摩尔浓度分别为 $m_{\\mathrm{NaCl}}=5$ 和 $m_{\\mathrm{CaCl_2}}=1$，得到的主体离子质量摩尔浓度为 $m_{\\mathrm{Na^+}}=5$，$m_{\\mathrm{Ca^{2+}}}=1$ 和 $m_{\\mathrm{Cl^-}}=7$。在这些盐度下，测得的平均活度系数约为 $\\gamma_{\\mathrm{Na^+}}\\approx 0.7$，$\\gamma_{\\mathrm{Ca^{2+}}}\\approx 0.25$ 和 $\\gamma_{\\mathrm{Cl^-}}\\approx 0.7$。在这些条件下，水的静态相对介电常数因介电衰减而降至 $\\varepsilon_r\\approx 60$。\n\n在Gouy–Chapman扩散层描述中，德拜屏蔽参数 $\\kappa$ 决定了电势的特征衰减长度 $\\kappa^{-1}$。考虑在这种盐水中，主体组成如何进入屏蔽参数的两种建模选择：一种是基于浓度（质量摩尔浓度或体积摩尔浓度）定义离子强度 $I$，另一种是用离子活度 $a_i=\\gamma_i c_i$ 替代浓度，以试图解释高离子强度下的非理想性。请批判性地评估这些选择对该系统中 $\\kappa^{-1}$ 的影响，并确定将非理想性纳入 $\\kappa$ 的科学上适当的方法。\n\n对于所描述的这种高离子强度盐水，哪个陈述最能反映正确的评估？\n\nA. 离子强度应基于浓度定义；在 $I$ 中用活度 $a_i$ 替代浓度在量纲上是不一致的，并且当 $\\gamma_i1$ 时，会减小计算出的 $I$ 值，从而人为地增加 $\\kappa^{-1}$。非理想性应通过介电常数和从超额化学势导出的热力学因子来纳入，而不是通过用 $a_i$ 重新定义 $I$。\n\nB. 因为静电屏蔽受化学势支配，所以离子强度应使用活度 $a_i$ 定义，这会正确地产生更小的 $\\kappa^{-1}$，与高盐度下更强的屏蔽作用一致。\n\nC. 在给定盐度下，$\\gamma_i\\approx 1$，因此用活度替代浓度对 $\\kappa^{-1}$ 的影响可以忽略不计，非理想性可以被忽略。\n\nD. 在离子强度中使用活度会同时降低 $I$ 和相对介电常数，这会增加 $\\kappa$ 并减小 $\\kappa^{-1}$，从而正确地使非理想盐水中的扩散层变薄。\n\nE. 非理想性完全由Stern层电容捕获；因此，扩散层屏蔽长度 $\\kappa^{-1}$ 对 $I$ 是用浓度还是活度定义不敏感。",
            "solution": "问题陈述已经过验证，被认为是有效的。它具有科学依据，问题提出得很好，并包含足够、一致的信息来解决所提出的概念性问题。该问题涉及在Gouy-Chapman-Stern模型的背景下，浓电解质溶液中德拜屏蔽参数 $\\kappa$ 的正确理论公式。\n\n德拜屏蔽长度 $\\kappa^{-1}$ 是电解质溶液理论中的一个基本概念，源于线性化的Poisson-Boltzmann方程。静电势 $\\psi$ 的控制方程是泊松方程 $\\nabla^2 \\psi = -\\rho_e / (\\varepsilon_0 \\varepsilon_r)$，其中 $\\rho_e$ 是局部体积电荷密度，$\\varepsilon_0$ 是真空介电常数，$\\varepsilon_r$ 是介质的相对介电常数。\n\n电荷密度由所有离子种类的总和给出：$\\rho_e = \\sum_i z_i e n_i$，其中 $z_i$ 是离子种类 $i$ 的整数电荷，$e$ 是基本电荷，$n_i$ 是种类 $i$ 的局部数浓度（单位体积的离子数）。关键点在于，$\\rho_e$ 是单位体积内电荷载流子物理*数量*的函数，该数量与其浓度成正比，而不是其热力学活度。\n\n在Gouy-Chapman模型中，局部离子浓度 $n_i$ 通过玻尔兹曼因子与主体浓度 $n_{i, \\infty}$ 相关联，$n_i = n_{i, \\infty} \\exp(-z_i e \\psi / (k_B T))$，其中 $k_B$ 是玻尔兹曼常数，$T$ 是绝对温度。对于小电势，指数可以线性化，$\\exp(-x) \\approx 1-x$。将其代入泊松方程，得到线性化的Poisson-Boltzmann（或Debye-Hückel）方程，$\\nabla^2 \\psi = \\kappa^2 \\psi$。德拜屏蔽参数的平方 $\\kappa^2$ 定义为：\n$$ \\kappa^2 = \\frac{e^2}{\\varepsilon_0 \\varepsilon_r k_B T} \\sum_i n_{i, \\infty} z_i^2 $$\n总和 $\\sum_i n_{i, \\infty} z_i^2$ 与离子强度 $I$ 直接相关。离子强度通常基于摩尔浓度定义，$I_c = \\frac{1}{2} \\sum_i c_i z_i^2$，其中 $c_i$ 是摩尔浓度（单位为 $\\mathrm{mol/m^3}$ 或 $\\mathrm{mol/L}$）。由于 $n_{i, \\infty} = c_i N_A$（其中 $N_A$ 是阿伏伽德罗常数），我们可以写出：\n$$ \\kappa^2 = \\frac{2 e^2 N_A}{\\varepsilon_0 \\varepsilon_r k_B T} I_c $$\n从这个基本关系可以清楚地看出，$\\kappa$ 与离子强度的平方根成正比，$\\kappa \\propto \\sqrt{I_c}$，而屏蔽长度则成反比，$\\kappa^{-1} \\propto 1/\\sqrt{I_c}$。\n\n问题建议考虑一种基于活度 $a_i = \\gamma_i c_i$ 的离子强度替代定义，其中 $\\gamma_i$ 是活度系数。我们将这个假设的离子强度表示为 $I_a = \\frac{1}{2} \\sum_i a_i z_i^2$。问题指出，对于给定的高盐度盐水，活度系数小于1（例如，$\\gamma_{\\mathrm{Na^+}}\\approx 0.7$，$\\gamma_{\\mathrm{Ca^{2+}}}\\approx 0.25$，$\\gamma_{\\mathrm{Cl^-}}\\approx 0.7$）。因此，用活度替代浓度将得到一个更低的离子强度值：$I_a  I_c$。\n\n如果错误地在 $\\kappa$ 的公式中使用 $I_a$，得到的屏蔽参数（我们称之为 $\\kappa_a$）将小于正确的参数 $\\kappa_c$（基于浓度）。由于 $\\kappa_a^2 \\propto I_a$ 且 $\\kappa_c^2 \\propto I_c$，因此 $\\kappa_a  \\kappa_c$。这意味着计算出的屏蔽长度 $(\\kappa_a)^{-1} > (\\kappa_c)^{-1}$。这表明在离子强度的定义中使用活度会人为地*增加*计算出的屏蔽长度，意味着*更弱*的屏蔽作用。这在物理上是不正确的；在高离子强度下，强的离子-离子相关性导致更有效的屏蔽，从而使扩散层*更薄*（屏蔽长度更小）。\n\n在此框架内，解释浓溶液中非理想性的科学上适当的方法不是用活度重新定义离子强度。相反，需要更高级的修正：\n1.  **介电衰减**：问题正确地指出了使用一个降低的相对介电常数 $\\varepsilon_r \\approx 60$，低于纯水的约 $\\approx 80$。从公式 $\\kappa^2 \\propto 1/\\varepsilon_r$ 可知，较小的 $\\varepsilon_r$ 导致较大的 $\\kappa$，从而得到一个更小、物理上更真实的 $\\kappa^{-1}$。\n2.  **超额化学势**：需要修改玻尔兹曼分布以考虑超额化学势（离子-离子相关性、有限离子尺寸）。这导致了修正的Poisson-Boltzmann方程。修正项通常被称为“热力学因子”，并从浓电解质理论（例如，Pitzer方程、Mean Spherical Approximation）中导出。这些修正通常会增强屏蔽效应，导致比简单的Debye-Hückel理论预测的更小的衰减长度。\n\n基于此分析，我们评估每个选项：\n\n**A. 离子强度应基于浓度定义；在 $I$ 中用活度 $a_i$ 替代浓度在量纲上是不一致的，并且当 $\\gamma_i1$ 时，会减小计算出的 $I$ 值，从而人为地增加 $\\kappa^{-1}$。非理想性应通过介电常数和从超额化学势导出的热力学因子来纳入，而不是通过用 $a_i$ 重新定义 $I$。**\n该陈述与我们的推导完全一致。它正确地指出 $I$ 应基于浓度。虽然“量纲上不一致”这一说法有待商榷，但从理论角度看，这种替代是根本错误的，因为它用一个热力学量（活度）代替了一个物理量（数密度）。它正确地指出了使用活度（当 $\\gamma_i  1$ 时）会减小 $I$ 并人为地增加 $\\kappa^{-1}$。最后，它正确地指出了包含非理想性的适当方法（介电常数修正和热力学因子）。该陈述科学准确且全面。**正确**。\n\n**B. 因为静电屏蔽受化学势支配，所以离子强度应使用活度 $a_i$ 定义，这会正确地产生更小的 $\\kappa^{-1}$，与高盐度下更强的屏蔽作用一致。**\n该陈述包含多个错误。首先，认为屏蔽“受化学势支配”从而证明在 $\\kappa$ 的定义中用活度替代浓度是合理的，这是对底层物理的误解。其次，更关键的是，它声称使用活度会产生*更小*的 $\\kappa^{-1}$。正如我们所展示的，对于 $\\gamma_i  1$，使用活度会导致更小的 $I$、更小的 $\\kappa$，从而导致*更大*的 $\\kappa^{-1}$。该陈述的结论与实际结果在数学上是相反的。**不正确**。\n\n**C. 在给定盐度下，$\\gamma_i\\approx 1$，因此用活度替代浓度对 $\\kappa^{-1}$ 的影响可以忽略不计，非理想性可以被忽略。**\n该陈述在事实上是错误的。问题明确提供了与1显著不同的活度系数（$\\gamma_{\\mathrm{Na^+}}\\approx 0.7$，$\\gamma_{\\mathrm{Ca^{2+}}}\\approx 0.25$，$\\gamma_{\\mathrm{Cl^-}}\\approx 0.7$）。溶液的质量摩尔离子强度为 $I_m = \\frac{1}{2}\\sum_i m_i z_i^2 = \\frac{1}{2}[5(1)^2 + 1(2)^2 + 7(-1)^2] = \\frac{1}{2}(5+4+7) = 8 \\, \\mathrm{mol/kg}$。在如此极高的离子强度下，非理想效应占主导地位，不能被忽略。该陈述的前提与所提供的数据相矛盾。**不正确**。\n\n**D. 在离子强度中使用活度会同时降低 $I$ 和相对介电常数，这会增加 $\\kappa$ 并减小 $\\kappa^{-1}$，从而正确地使非理想盐水中的扩散层变薄。**\n该陈述有几个缺陷。虽然使用活度确实会减小计算出的 $I$（对于 $\\gamma_i  1$），但它错误地声称这会*增加* $\\kappa$；更小的 $I$ 会导致*更小*的 $\\kappa$。此外，该陈述毫无道理地将“在 $I$ 中使用活度”这一计算选择与相对介电常数 $\\varepsilon_r$ 的物理值联系起来。介电常数是溶液的物理性质，取决于浓度，而不是一个会根据人们如何选择计算 $I$ 而改变的参数。**不正确**。\n\n**E. 非理想性完全由Stern层电容捕获；因此，扩散层屏蔽长度 $\\kappa^{-1}$ 对 $I$ 是用浓度还是活度定义不敏感。**\n该陈述曲解了Gouy-Chapman-Stern模型。Stern层解释了界面处的特定吸附和有限离子尺寸，这些是重要的非理想效应。然而，它并未捕获所有的非理想性，特别是在主体溶液和扩散层中的效应，如离子-离子相关性和介电衰减，这些直接决定了 $\\kappa$。根据其定义，扩散层屏蔽长度 $\\kappa^{-1}$ 高度依赖于主体溶液的离子强度 $I$。因此，它对如何定义和计算 $I$ 非常敏感。**不正确**。",
            "answer": "$$\\boxed{A}$$"
        }
    ]
}