{"hands_on_practices": [{"introduction": "沸点升高是一个在食品科学和化学工程中随处可见的现象。本练习将带你进入一个食品化学家的角色，通过一个浓缩植物汁液制作糖浆的实际场景，来应用沸点升高的基本原理。这个练习不仅能帮助你掌握核心公式 $\\Delta T_b = K_b m$ 的计算，还能训练你如何处理涉及质量百分比和浓度变化的综合问题 [@problem_id:1984380]。", "problem": "一位食品化学家正在监督使用未加工的植物汁液生产一种特制糖浆的过程。该汁液可被模拟为蔗糖（$C_{12}H_{22}O_{11}$）的水溶液。此过程包括将初始批次的汁液加热煮沸，蒸发掉一部分水，从而进行浓缩。\n\n已知以下信息：\n- 初始批次的汁液总质量为 $50.00 \\text{ kg}$，其中蔗糖的质量分数为 $2.800\\%$。\n- 在恒定大气压（1 atm）下，于蒸发器中对该汁液进行浓缩，直到所得糖浆的总质量减少到 $4.900 \\text{ kg}$。\n- 蔗糖是一种非挥发性、非电解质溶质。\n- 蔗糖的摩尔质量为 $342.30 \\text{ g/mol}$。\n- 纯水的标准沸点是 $100.00^{\\circ}\\text{C}$。\n- 水的沸点升高常数（$K_b$）为 $0.5120^{\\circ}\\text{C} \\cdot \\text{kg/mol}$。\n\n计算最终浓缩糖浆的沸点。请用摄氏度（$^{\\circ}\\text{C}$）表示结果，并四舍五入至四位有效数字。", "solution": "我们应用溶质质量守恒定律和溶液沸点升高原理。\n\n设初始总质量为 $m_{\\text{tot},0} = 50.00~\\text{kg}$，蔗糖质量分数为 $x_{\\text{s}} = 0.02800$。则蔗糖的质量为\n$$\nm_{\\text{s}} = x_{\\text{s}}\\, m_{\\text{tot},0} = 0.02800 \\times 50.00 = 1.400~\\text{kg}.\n$$\n蔗糖不具挥发性，因此其质量 $m_{\\text{s}}$ 保持不变。蒸发浓缩后，最终总质量为 $m_{\\text{tot},f} = 4.900~\\text{kg}$，因此水的最终质量为\n$$\nm_{\\text{w},f} = m_{\\text{tot},f} - m_{\\text{s}} = 4.900 - 1.400 = 3.500~\\text{kg}.\n$$\n\n蔗糖的物质的量为\n$$\nn_{\\text{s}} = \\frac{m_{\\text{s}}}{M_{\\text{s}}} = \\frac{1.400~\\text{kg} \\times 1000~\\text{g/kg}}{342.30~\\text{g/mol}} = \\frac{1400}{342.30}~\\text{mol}.\n$$\n溶液的质量摩尔浓度（溶质的物质的量除以溶剂的千克数）为\n$$\nm = \\frac{n_{\\text{s}}}{m_{\\text{w},f}} = \\frac{1400/342.30}{3.500} = \\frac{1400}{342.30 \\times 3.500} = \\frac{1400}{1198.05}~\\text{mol/kg}.\n$$\n\n对于非电解质溶质，沸点升高由沸点升高公式给出\n$$\n\\Delta T_{b} = i\\, K_{b}\\, m,\n$$\n其中，对于蔗糖，$i=1$ 且 $K_{b} = 0.5120^{\\circ}\\text{C}\\cdot\\text{kg/mol}$。因此，\n$$\n\\Delta T_{b} = 0.5120 \\times \\frac{1400}{1198.05}~^{\\circ}\\text{C} = \\frac{0.5120 \\times 1400}{1198.05}~^{\\circ}\\text{C} \\approx 0.598305536~^{\\circ}\\text{C}.\n$$\n溶液在 $1~\\text{atm}$ 压强下的沸点等于纯水的沸点加上此沸点升高值：\n$$\nT_{b,\\text{solution}} = 100.00~^{\\circ}\\text{C} + \\Delta T_{b} \\approx 100.00 + 0.598305536 = 100.598305536~^{\\circ}\\text{C}.\n$$\n将结果四舍五入至四位有效数字，得到 $100.6~^{\\circ}\\text{C}$。", "answer": "$$\\boxed{100.6}$$", "id": "1984380"}, {"introduction": "范特霍夫因子 $i$ 不仅能描述溶质的解离，还能揭示分子在溶液中的缔合行为。当溶质分子（如某些羧酸）在非极性溶剂中形成二聚体时，溶液中独立粒子的有效数量会减少，导致范特霍夫因子 $i  1$。通过这个分析化学的实例，你将学会如何利用实验测得的沸点升高数据，反推出有效的范特霍夫因子，从而深入理解溶质分子间的相互作用 [@problem_id:1984376]。", "problem": "一位分析化学家正在研究丙酮酸（$C_3H_4O_3$，摩尔质量 = 88.06 g/mol）在苯中的依数性。已知某些羧酸在溶于苯等非极性溶剂时，会因分子间氢键而缔合形成二聚体。为量化此效应，该化学家将 10.00 g 丙酮酸溶解在 250.0 g 苯中制备了一种溶液。测得该溶液的沸点比纯苯升高了 $0.750^{\\circ}\\text{C}$。苯的摩尔沸点升高常数（$K_b$）为 $2.53^{\\circ}\\text{C}\\cdot\\text{kg/mol}$。\n\n根据这些实验数据，计算丙酮酸在该苯溶液中的有效范特霍夫因子（$i$）。将您的最终答案四舍五入至三位有效数字。", "solution": "对于非电解质或缔合溶质，沸点升高由以下依数性关系式给出：\n$$\n\\Delta T_{b} = i K_{b} m,\n$$\n其中 $i$ 是范特霍夫因子，$K_{b}$ 是溶剂的沸点升高常数，$m$ 是溶质颗粒的质量摩尔浓度。\n\n首先，计算溶解的丙酮酸的摩尔数：\n$$\nn_{\\text{solute}} = \\frac{m_{\\text{solute}}}{M} = \\frac{10.00~\\text{g}}{88.06~\\text{g/mol}} \\approx 0.113559~\\text{mol}.\n$$\n\n将苯的质量转换为千克，并计算质量摩尔浓度：\n$$\nm_{\\text{solvent}} = 250.0~\\text{g} = 0.2500~\\text{kg},\n$$\n$$\nm = \\frac{n_{\\text{solute}}}{m_{\\text{solvent}}} = \\frac{0.113559~\\text{mol}}{0.2500~\\text{kg}} \\approx 0.454236~\\text{mol/kg}.\n$$\n\n使用测得的沸点升高 $\\Delta T_{b} = 0.750^{\\circ}\\text{C}$ 和 $K_{b} = 2.53^{\\circ}\\text{C}\\cdot\\text{kg/mol}$ 求解范特霍夫因子：\n$$\ni = \\frac{\\Delta T_{b}}{K_{b}\\, m} = \\frac{0.750}{2.53 \\times 0.454236} \\approx 0.6526.\n$$\n\n四舍五入至三位有效数字，得到\n$$\ni \\approx 0.653.\n$$\n这个小于 1 的值与丙酮酸在苯中发生缔合（例如，二聚化作用）的情况一致，缔合会减少溶质颗粒的数量。", "answer": "$$\\boxed{0.653}$$", "id": "1984376"}, {"introduction": "科学探索往往始于理论预测与实验结果的差异。本练习提出了一个发人深省的情景：为什么将乙醇（一种挥发性溶质）加入水中，溶液的沸点反而可能低于纯水？这个看似矛盾的现象，直击了沸点升高公式 $\\Delta T_b = i K_b m$ 的一个基本假设——溶质必须是非挥发性的。通过分析此问题，你将能区分挥发性与非挥发性溶质对溶液总蒸气压的不同影响，从而更深刻地理解依数性定律的适用边界 [@problem_id:1984368]。", "problem": "一名学生受命预测将大量乙醇($\\text{C}_2\\text{H}_5\\text{OH}$)溶于水后所配制的水溶液的沸点。该学生使用了依数性质的标准沸点升高公式 $\\Delta T_b = i K_b m$，其中 $\\Delta T_b$ 是沸点的变化量，$i$ 是范特霍夫因子（对于乙醇，假定为1），$K_b$ 是水的沸点升高常数，$m$ 是乙醇的重量摩尔浓度。基于此计算，该学生预测溶液的沸点将高于纯水的正常沸点（在1个标准大气压下为$100.00^{\\circ}\\text{C}$）。\n\n然而，在仔细进行实验后，该学生惊讶地发现，溶液的实际沸点*低于*$100.00^{\\circ}\\text{C}$。该学生对重量摩尔浓度的计算和公式的应用在算术上是正确的。\n\n下列哪个陈述为学生的预测与实验结果之间的差异提供了最准确和最根本的解释？\n\nA. 乙醇的范特霍夫因子不为1；它远大于1，因为乙醇分子在水中会解离。\n\nB. 沸点升高公式 $\\Delta T_b = i K_b m$ 仅对理想溶液有效，而乙醇-水混合物表现出强烈的非理想行为，从而抑制了沸点。\n\nC. 沸点升高公式 $\\Delta T_b = i K_b m$ 的推导，从根本上假设了溶质是非挥发性的。乙醇是一种挥发性物质，它会对体系贡献自身的蒸气压，而该公式忽略了这一点。\n\nD. 水的沸点升高常数 $K_b$ 仅适用于离子溶质，对于像乙醇这样的分子溶质，应该使用一个不同的常数。\n\nE. 乙醇在水中的溶解是一个强烈的吸热过程，这会使溶液冷却，并降低达到沸点所需的能量。", "solution": "标准沸点升高关系式 $\\Delta T_{b} = i K_{b} m$ 是在一个基本假设下推导出来的，即溶质是非挥发性的，因此它对气相没有蒸气贡献。在这种情况下，根据溶剂的 Raoult 定律，溶液的蒸气压为\n$$\nP_{\\text{solution}}(T) = x_{1} P_{1}^{*}(T),\n$$\n其中 $x_{1}$ 是溶剂（水）的摩尔分数，$P_{1}^{*}(T)$ 是纯水在温度 $T$ 下的饱和蒸气压。对于在外部压力 $P_{\\text{ext}}$ 下的沸腾，条件是 $P_{\\text{solution}}(T_{b,\\text{soln}}) = P_{\\text{ext}}$。因为 $x_{1}  1$，所以要求 $P_{1}^{*}(T_{b,\\text{soln}})  P_{\\text{ext}}$，这发生在比纯溶剂正常沸点 $T_{b}^{(1)}$（满足 $P_{1}^{*}(T_{b}^{(1)}) = P_{\\text{ext}}$）更高的温度下。这导致 $\\Delta T_{b}  0$ 并得出公式 $\\Delta T_{b} = i K_{b} m$。\n\n然而，乙醇是一种挥发性溶质。对于一个表现出理想行为的、由两种挥发性组分组成的溶液，根据 Dalton 定律和 Raoult 定律，总蒸气压为\n$$\nP_{\\text{tot}}(T) = x_{1} P_{1}^{*}(T) + x_{2} P_{2}^{*}(T),\n$$\n其中 $x_{2}$ 是乙醇的摩尔分数，$P_{2}^{*}(T)$ 是纯乙醇在温度 $T$ 下的饱和蒸气压。沸腾条件是\n$$\nx_{1} P_{1}^{*}(T_{b,\\text{mix}}) + x_{2} P_{2}^{*}(T_{b,\\text{mix}}) = P_{\\text{ext}}.\n$$\n设 $T_{b}^{(1)}$ 表示纯水的正常沸点，因此 $P_{1}^{*}(T_{b}^{(1)}) = P_{\\text{ext}}$。因为对于所有相关温度 $T$，$x_{2}  0$ 且 $P_{2}^{*}(T)  0$，所以关系式\n$$\nx_{1} P_{1}^{*}(T_{b,\\text{mix}}) = P_{\\text{ext}} - x_{2} P_{2}^{*}(T_{b,\\text{mix}})  P_{\\text{ext}}\n$$\n意味着\n$$\nP_{1}^{*}(T_{b,\\text{mix}})  P_{1}^{*}(T_{b}^{(1)}).\n$$\n由于 $P_{1}^{*}(T)$ 是 $T$ 的严格递增函数，因此可以得出\n$$\nT_{b,\\text{mix}}  T_{b}^{(1)}.\n$$\n因此，在存在像乙醇这样的挥发性溶质时，总蒸气压可以在低于纯水正常沸点的温度下达到 $P_{\\text{ext}}$，所以该混合物可以在低于纯水沸点的温度下沸腾。沸点升高公式 $\\Delta T_{b} = i K_{b} m$ 不适用，因为它的推导通过假设溶质是非挥发性的而忽略了溶质的蒸气压。\n\n因此，最准确和最根本的解释是，该公式的推导假设了溶质是非挥发性的，而乙醇是挥发性的，并对蒸气压有贡献。这对应于选项 C。其他选项不一致：乙醇不会解离（A是错误的），解释观察到的沸点降低现象并不需要非理想性，因为对于理想的挥发性混合物，这种效应已经存在（B不是根本原因），$K_{b}$ 并不局限于离子溶质（D是错误的），混合焓不决定平衡沸点（E与该差异无关）。", "answer": "$$\\boxed{C}$$", "id": "1984368"}]}