{"hands_on_practices": [{"introduction": "量化代谢产热是研究体温调节的基石。间接量热法是一种核心技术，它通过测量耗氧量来推算能量释放。本练习将指导你如何从基本原理出发，根据不同代谢底物（碳水化合物和脂肪）的化学计量关系，推导出特定呼吸商（$RQ$）下的氧气能量当量，这是准确解读代谢数据的关键技能。[@problem_id:2619185]", "problem": "为通过间接量热法量化代谢产热，在一只处于静息状态的内温小型哺乳动物上进行了稳态条件下的研究。在标准温度、压力、干燥（STPD）条件下，测得耗氧量为 $\\dot{V}\\mathrm{O}_2 = 0.250\\,\\mathrm{L}\\,\\mathrm{min}^{-1}$。呼吸商（RQ），定义为 $RQ = \\dot{V}\\mathrm{CO}_2/\\dot{V}\\mathrm{O}_2$，测得为 $RQ = 0.85$。假设代谢底物仅为碳水化合物（葡萄糖）和脂肪（棕榈酸酯），蛋白质的贡献可忽略不计。使用能量守恒和底物化学计量来确定氧的能量当量并计算代谢产热。\n\n使用以下在标准条件下有效的完全燃烧反应和标准燃烧焓（产物水为液态）：\n- 碳水化合物（葡萄糖）：$\\mathrm{C}_6\\mathrm{H}_{12}\\mathrm{O}_6 + 6\\,\\mathrm{O}_2 \\to 6\\,\\mathrm{CO}_2 + 6\\,\\mathrm{H}_2\\mathrm{O}$，$\\Delta H_{\\mathrm{comb,c}} = 2805\\,\\mathrm{kJ}\\,\\mathrm{mol}^{-1}$。\n- 脂肪（棕榈酸酯）：$\\mathrm{C}_{16}\\mathrm{H}_{32}\\mathrm{O}_2 + 23\\,\\mathrm{O}_2 \\to 16\\,\\mathrm{CO}_2 + 16\\,\\mathrm{H}_2\\mathrm{O}$，$\\Delta H_{\\mathrm{comb,f}} = 9974\\,\\mathrm{kJ}\\,\\mathrm{mol}^{-1}$。\n\n假设在STPD条件下气体为理想气体，其摩尔体积为 $V_m = 22.414\\,\\mathrm{L}\\,\\mathrm{mol}^{-1}$。将测得的RQ视为由碳水化合物和脂肪的混合物产生，其分数贡献分别为 $f_{\\mathrm{c}}$ 和 $f_{\\mathrm{f}} = 1 - f_{\\mathrm{c}}$，其中混合物的呼吸商遵循 $RQ = f_{\\mathrm{c}} \\cdot 1.0 + (1 - f_{\\mathrm{c}})\\cdot 0.7$。基于这些前提，不使用任何预先制表的氧的热量当量，从第一性原理推导出针对测得的RQ的氧的能量当量（单位为 $\\mathrm{kJ}\\,\\mathrm{L}^{-1}$），然后计算代谢产热率 $\\dot{Q}$（单位为 $\\mathrm{W}$）。\n\n以瓦特（$\\mathrm{W}$）为单位表示最终答案，并将答案四舍五入到四位有效数字。", "solution": "问题陈述经核实科学上合理、内容自洽且提法明确。这是一个间接量热法中的标准问题，可以从化学计量学和热力学的第一性原理出发求解。我们将进行严谨的推导。\n\n代谢产热率 $\\dot{Q}$ 是耗氧率 $\\dot{V}\\mathrm{O}_2$ 与氧的能量当量 $EE_{\\mathrm{O}_2}$ 的乘积。能量当量取决于被氧化的特定底物。由于该动物正在代谢碳水化合物和脂肪的混合物，我们必须首先确定每种底物对耗氧量的分数贡献，这可以从呼吸商 $RQ$ 推断出来。\n\n首先，我们根据给定的燃烧反应确定纯底物的理论RQ值。RQ是产生的二氧化碳与消耗的氧气的摩尔比。\n对于碳水化合物（葡萄糖，$\\mathrm{C}_6\\mathrm{H}_{12}\\mathrm{O}_6$）：\n$$\n\\mathrm{C}_6\\mathrm{H}_{12}\\mathrm{O}_6 + 6\\,\\mathrm{O}_2 \\to 6\\,\\mathrm{CO}_2 + 6\\,\\mathrm{H}_2\\mathrm{O}\n$$\n碳水化合物的呼吸商 $RQ_{\\mathrm{c}}$ 为：\n$$\nRQ_{\\mathrm{c}} = \\frac{\\text{moles of } \\mathrm{CO}_2}{\\text{moles of } \\mathrm{O}_2} = \\frac{6}{6} = 1.0\n$$\n对于脂肪（棕榈酸酯，$\\mathrm{C}_{16}\\mathrm{H}_{32}\\mathrm{O}_2$）：\n$$\n\\mathrm{C}_{16}\\mathrm{H}_{32}\\mathrm{O}_2 + 23\\,\\mathrm{O}_2 \\to 16\\,\\mathrm{CO}_2 + 16\\,\\mathrm{H}_2\\mathrm{O}\n$$\n脂肪的呼吸商 $RQ_{\\mathrm{f}}$ 为：\n$$\nRQ_{\\mathrm{f}} = \\frac{\\text{moles of } \\mathrm{CO}_2}{\\text{moles of } \\mathrm{O}_2} = \\frac{16}{23} \\approx 0.6957\n$$\n问题提供了一个使用 $RQ_{\\mathrm{f}} = 0.7$ 的简化模型，我们必须使用此值。测得的总RQ是各个底物RQ的加权平均值，其中权重因子 $f_{\\mathrm{c}}$ 和 $f_{\\mathrm{f}}$ 分别是用于氧化碳水化合物和脂肪的耗氧量占总耗氧量的分数。\n设测得的RQ为 $RQ_{\\mathrm{mix}} = 0.85$。问题给出了以下关系：\n$$\nRQ_{\\mathrm{mix}} = f_{\\mathrm{c}} \\cdot RQ_{\\mathrm{c}} + (1 - f_{\\mathrm{c}}) \\cdot RQ_{\\mathrm{f}}\n$$\n代入已知值：\n$$\n0.85 = f_{\\mathrm{c}} \\cdot 1.0 + (1 - f_{\\mathrm{c}}) \\cdot 0.7\n$$\n我们求解 $f_{\\mathrm{c}}$：\n$$\n0.85 = f_{\\mathrm{c}} + 0.7 - 0.7 \\cdot f_{\\mathrm{c}}\n$$\n$$\n0.15 = 0.3 \\cdot f_{\\mathrm{c}}\n$$\n$$\nf_{\\mathrm{c}} = \\frac{0.15}{0.3} = 0.5\n$$\n因此，用于碳水化合物代谢的耗氧分数为 $f_{\\mathrm{c}} = 0.5$，用于脂肪代谢的耗氧分数为 $f_{\\mathrm{f}} = 1 - f_{\\mathrm{c}} = 0.5$。\n\n接下来，我们推导每种底物的氧的能量当量，即每消耗一升 $\\mathrm{O}_2$ 所释放的能量。我们使用给定的标准燃烧焓和STPD条件下理想气体的摩尔体积 $V_m = 22.414\\,\\mathrm{L}\\,\\mathrm{mol}^{-1}$。\n\n对于碳水化合物：\n$$\nEE_{\\mathrm{c}} = \\frac{\\Delta H_{\\mathrm{comb,c}}}{(\\text{moles of } \\mathrm{O}_2) \\cdot V_m} = \\frac{2805\\,\\mathrm{kJ}}{6\\,\\mathrm{mol} \\cdot 22.414\\,\\mathrm{L}\\,\\mathrm{mol}^{-1}} = \\frac{2805}{134.484}\\,\\mathrm{kJ}\\,\\mathrm{L}^{-1}\n$$\n对于脂肪：\n$$\nEE_{\\mathrm{f}} = \\frac{\\Delta H_{\\mathrm{comb,f}}}{(\\text{moles of } \\mathrm{O}_2) \\cdot V_m} = \\frac{9974\\,\\mathrm{kJ}}{23\\,\\mathrm{mol} \\cdot 22.414\\,\\mathrm{L}\\,\\mathrm{mol}^{-1}} = \\frac{9974}{515.522}\\,\\mathrm{kJ}\\,\\mathrm{L}^{-1}\n$$\n混合物的总氧能量当量 $EE_{\\mathrm{mix}}$ 是使用分数 $f_{\\mathrm{c}}$ 和 $f_{\\mathrm{f}}$ 对单个当量值进行的加权平均：\n$$\nEE_{\\mathrm{mix}} = f_{\\mathrm{c}} \\cdot EE_{\\mathrm{c}} + f_{\\mathrm{f}} \\cdot EE_{\\mathrm{f}}\n$$\n$$\nEE_{\\mathrm{mix}} = 0.5 \\cdot \\left(\\frac{2805}{134.484}\\right) + 0.5 \\cdot \\left(\\frac{9974}{515.522}\\right)\\,\\mathrm{kJ}\\,\\mathrm{L}^{-1}\n$$\n$$\nEE_{\\mathrm{mix}} = 0.5 \\cdot (20.8575... + 19.3474...)\\,\\mathrm{kJ}\\,\\mathrm{L}^{-1}\n$$\n$$\nEE_{\\mathrm{mix}} \\approx 20.1025\\,\\mathrm{kJ}\\,\\mathrm{L}^{-1}\n$$\n这就是给定代谢状态下氧的能量当量。\n\n最后，我们通过将总耗氧率 $\\dot{V}\\mathrm{O}_2$ 乘以混合能量当量 $EE_{\\mathrm{mix}}$ 来计算总代谢产热率 $\\dot{Q}$。给定的耗氧量为 $\\dot{V}\\mathrm{O}_2 = 0.250\\,\\mathrm{L}\\,\\mathrm{min}^{-1}$。\n$$\n\\dot{Q} = \\dot{V}\\mathrm{O}_2 \\cdot EE_{\\mathrm{mix}}\n$$\n$$\n\\dot{Q} = 0.250\\,\\mathrm{L}\\,\\mathrm{min}^{-1} \\cdot 20.1025\\,\\mathrm{kJ}\\,\\mathrm{L}^{-1} \\approx 5.0256\\,\\mathrm{kJ}\\,\\mathrm{min}^{-1}\n$$\n问题要求答案以瓦特（$\\mathrm{W}$）为单位，其中 $1\\,\\mathrm{W} = 1\\,\\mathrm{J}\\,\\mathrm{s}^{-1}$。我们进行单位转换：\n$$\n\\dot{Q} = 5.0256\\,\\frac{\\mathrm{kJ}}{\\mathrm{min}} \\cdot \\frac{1000\\,\\mathrm{J}}{1\\,\\mathrm{kJ}} \\cdot \\frac{1\\,\\mathrm{min}}{60\\,\\mathrm{s}}\n$$\n$$\n\\dot{Q} = \\frac{5025.6}{60}\\,\\mathrm{J}\\,\\mathrm{s}^{-1} \\approx 83.760\\,\\mathrm{W}\n$$\n按要求将结果四舍五入到四位有效数字，得到 $83.76\\,\\mathrm{W}$。", "answer": "$$\n\\boxed{83.76}\n$$", "id": "2619185"}, {"introduction": "在量化了产热率之后，下一步是建立热量交换模型，以理解生物体如何与环境互动。一个经典的生物物理模型假设，在稳态下，内温动物的代谢产热（$M$）等于通过传导和对流散失到环境中的热量，后者与体温和环境的温差成正比。本练习将向你展示如何从实验数据中提取关键的生理参数，如最小热导（$C$）和下临界温度（$T_{lc}$），从而连接物理理论与生物观测。[@problem_id:2619155]", "problem": "在一个开放式呼吸测量室中研究了一只静息的有胎盘哺乳动物，以量化其温度调节能量学。在整个试验过程中，该动物保持了稳定的核心体温 $T_b = 37.00^{\\circ}\\mathrm{C}$。在多个环境温度 $T_a$（单位：${}^{\\circ}\\mathrm{C}$）下测量了代谢产热 $M$（单位：$\\mathrm{W}$）。在冷暴露范围内，姿势和立毛是固定的，蒸发失热可忽略不计，此时 $M$ 对 $T_a$ 的最佳拟合线性回归为 $M = \\alpha_{\\mathrm{cold}} + \\beta_{\\mathrm{cold}}\\,T_a$，斜率 $\\beta_{\\mathrm{cold}} = -8.000 \\times 10^{-2}\\ \\mathrm{W}\\,\\mathrm{K}^{-1}$，截距 $\\alpha_{\\mathrm{cold}} = 2.960\\ \\mathrm{W}$。在热中性区（其中干热导通过行为和自主神经调节，使代谢产热最小且近似恒定），回归斜率为 $\\beta_{\\mathrm{TNZ}} = -1.0 \\times 10^{-3}\\ \\mathrm{W}\\,\\mathrm{K}^{-1}$（为当前目的，可认为与零无异），平均代谢率为 $M_{\\mathrm{TNZ}} = 0.8000\\ \\mathrm{W}$。\n\n假设处于稳态能量平衡，蒸发失热可忽略不计，并且在下临界温度 $T_{lc}$ 以下，有效干热导 $C$ 是恒定的（最小），因此干性失热与身体和环境之间的温度梯度成正比。仅使用这些数据和基于物理热平衡的假设，计算最小干热导 $C$（以 $\\mathrm{W}\\,\\mathrm{K}^{-1}$ 为单位表示）并估算下临界温度 $T_{lc}$（以 ${}^{\\circ}\\mathrm{C}$ 为单位表示）。将两个所求量均四舍五入至四位有效数字。", "solution": "所提出的问题是生物物理生态学中的一个标准练习，其基础是热传递和能量平衡的原理。该问题在科学上是合理的、适定的，并包含一致、物理上现实的数据。因此，可以推导出解决方案。\n\n此分析的核心原理是稳态能量平衡方程，该方程规定，对于稳定的体温，代谢产热率（$M$）必须等于向环境失热的速率（$H_L$）。\n$$M = H_L$$\n问题指出，热量损失主要通过干性热传导和对流，并且可以建模为与身体（$T_b$）和周围环境（$T_a$）之间的温差成正比。这是牛顿冷却定律的应用：\n$$H_L = C(T_b - T_a)$$\n其中 $C$ 是有效干热导。\n\n问题描述了该哺乳动物的两个不同温度调节区：\n$1$. 热中性区（TNZ），其中代谢率最小且恒定。对于等于或高于下临界温度的环境温度（$T_a \\geq T_{lc}$），代谢率由 $M = M_{\\mathrm{TNZ}} = 0.8000\\ \\mathrm{W}$ 给出。\n$2$. 冷暴露范围，其中环境温度低于下临界温度（$T_a  T_{lc}$）。在此范围内，动物必须增加其代谢率以维持恒定的体温。数据提供了代谢率作为环境温度函数的线性关系：$M = \\alpha_{\\mathrm{cold}} + \\beta_{\\mathrm{cold}}\\,T_a$。\n\n我们的第一个目标是计算最小干热导 $C$。在冷暴露范围（$T_a  T_{lc}$）内，当隔热（姿势、立毛）最大化时，该热导是恒定的。\n在此范围内，我们可以将物理热平衡定律与经验线性回归方程相等同。\n热平衡方程为 $M = C(T_b - T_a)$。这可以重新整理为关于 $T_a$ 的线性形式：\n$$M = C\\,T_b - C\\,T_a$$\n给出的经验回归方程为：\n$$M = \\alpha_{\\mathrm{cold}} + \\beta_{\\mathrm{cold}}\\,T_a$$\n通过比较这两个关于 $M$ 作为 $T_a$ 函数的线性方程的系数，我们可以将物理参数 $C$ 与测得的回归斜率 $\\beta_{\\mathrm{cold}}$ 联系起来。物理模型的斜率为 $-C$。\n$$-C = \\beta_{\\mathrm{cold}}$$\n因此，最小干热导 $C$ 为：\n$$C = -\\beta_{\\mathrm{cold}}$$\n代入给定的 $\\beta_{\\mathrm{cold}} = -8.000 \\times 10^{-2}\\ \\mathrm{W}\\,\\mathrm{K}^{-1}$ 值：\n$$C = -(-8.000 \\times 10^{-2}\\ \\mathrm{W}\\,\\mathrm{K}^{-1}) = 8.000 \\times 10^{-2}\\ \\mathrm{W}\\,\\mathrm{K}^{-1}$$\n问题提供的数据是内部一致的。我们可以通过检查截距项来验证这一点。根据我们的比较，$\\alpha_{\\mathrm{cold}} = C\\,T_b$。使用我们计算出的 $C$ 和给定的 $T_b = 37.00^{\\circ}\\mathrm{C}$：\n$$C\\,T_b = (8.000 \\times 10^{-2}\\ \\mathrm{W}\\,\\mathrm{K}^{-1}) \\times (37.00\\ {}^{\\circ}\\mathrm{C}) = 2.960\\ \\mathrm{W}$$\n这与提供的截距 $\\alpha_{\\mathrm{cold}} = 2.960\\ \\mathrm{W}$ 相匹配，证实了模型和数据的一致性。\n\n我们的第二个目标是估算下临界温度 $T_{lc}$。下临界温度定义为热中性区和冷暴露范围边界处的环境温度。在此特定温度下，动物的最小（基础）代谢率恰好足以维持其体温，而无需额外的产热。因此，在 $T_a = T_{lc}$ 时，热平衡方程为：\n$$M_{\\mathrm{TNZ}} = C(T_b - T_{lc})$$\n我们可以重新整理此方程以求解 $T_{lc}$：\n$$T_b - T_{lc} = \\frac{M_{\\mathrm{TNZ}}}{C}$$\n$$T_{lc} = T_b - \\frac{M_{\\mathrm{TNZ}}}{C}$$\n现在我们代入已知值：$T_b = 37.00^{\\circ}\\mathrm{C}$，$M_{\\mathrm{TNZ}} = 0.8000\\ \\mathrm{W}$，以及我们计算出的值 $C = 8.000 \\times 10^{-2}\\ \\mathrm{W}\\,\\mathrm{K}^{-1}$。请注意，开尔文温差在数值上等于摄氏度温差。\n$$T_{lc} = 37.00^{\\circ}\\mathrm{C} - \\frac{0.8000\\ \\mathrm{W}}{8.000 \\times 10^{-2}\\ \\mathrm{W}\\,\\mathrm{K}^{-1}}$$\n$$T_{lc} = 37.00^{\\circ}\\mathrm{C} - 10.00\\ \\mathrm{K}$$\n由于计算涉及温差，我们可以写成：\n$$T_{lc} = 37.00^{\\circ}\\mathrm{C} - 10.00^{\\circ}\\mathrm{C} = 27.00^{\\circ}\\mathrm{C}$$\n问题要求四舍五入到四位有效数字。计算出的热导值为 $C = 0.08000\\ \\mathrm{W}\\,\\mathrm{K}^{-1}$，有四位有效数字。计算出的下临界温度为 $T_{lc} = 27.00^{\\circ}\\mathrm{C}$，也有四位有效数字。\n\n最终值为：\n最小干热导，$C = 8.000 \\times 10^{-2}\\ \\mathrm{W}\\,\\mathrm{K}^{-1}$。\n下临界温度，$T_{lc} = 27.00^{\\circ}\\mathrm{C}$。", "answer": "$$\\boxed{\\begin{pmatrix} 8.000 \\times 10^{-2}  27.00 \\end{pmatrix}}$$", "id": "2619155"}, {"introduction": "与通过代谢产热来维持体温的内温动物不同，外温动物的生理活动和运动表现直接受环境温度的制约。温度系数 $Q_{10}$ 是一个描述这种依赖关系的常用简化模型，但现实情况往往更为复杂。本练习旨在通过比较简单的 $Q_{10}$ 模型与更符合实际的运动表现曲线，培养你评估不同模型及其适用范围的能力，这对于理解外温动物的热生物学至关重要。[@problem_id:2619112]", "problem": "一种小型日行性蜥蜴（外温动物）在实验室条件下表现出依赖于温度的冲刺速度，在测量的短时间尺度内，其体温实际上等于环境温度。在适度的温度范围内，外温动物的许多生理和性能速率表现出近似的指数关系，这可以用 van 't Hoff 温度系数 $Q_{10}$ 来概括，其定义为温度每增加 $10\\,^{\\circ}\\mathrm{C}$ 时速率的倍数变化。\n\n为该蜥蜴的冲刺速度测量的经验运动性能曲线由一个单峰函数表示\n$$\nV(T) \\;=\\; V_{\\max}\\,\\exp\\!\\left(-\\frac{(T - T_{\\mathrm{opt}})^{2}}{2\\sigma^{2}}\\right),\n$$\n其参数为 $V_{\\max} = 1.8\\,\\mathrm{m\\,s^{-1}}$，$T_{\\mathrm{opt}} = 34\\,^{\\circ}\\mathrm{C}$，以及 $\\sigma = 10\\,^{\\circ}\\mathrm{C}$，在 $15\\,^{\\circ}\\mathrm{C}$ 到 $40\\,^{\\circ}\\mathrm{C}$ 的温度范围内提供了良好的拟合。假设 $Q_{10} = 2.0$ 表征了在 $T = 22\\,^{\\circ}\\mathrm{C}$ 附近的热敏感性。\n\n仅使用 $Q_{10}$ 的定义“速率因温度增加 $10\\,^{\\circ}\\mathrm{C}$ 而变化的因子”以及所提供的经验曲线，从第一性原理出发：\n\n- 推导由 $Q_{10}$ 蕴含的、在 $T_{1} = 22\\,^{\\circ}\\mathrm{C}$ 到 $T_{2} = 29\\,^{\\circ}\\mathrm{C}$ 区间内冲刺速度的预测倍数变化，\n- 根据给定的 $V(T)$ 计算在相同区间内的经验倍数变化，以及\n- 计算定义为如下的相对差异\n$$\nE \\;=\\; \\frac{\\displaystyle \\frac{V(T_{2})}{V(T_{1})} \\;-\\; \\left(\\text{$Q_{10}$ 预测值}\\right)}{\\left(\\text{$Q_{10}$ 预测值}\\right)}.\n$$\n\n只需报告 $E$ 的最终值，以纯小数形式表示（不带百分号），并四舍五入到 $4$ 位有效数字。无需报告其他任何量。", "solution": "问题陈述已经过验证，被认为是科学上合理、提法明确且客观的。它没有矛盾或含糊之处，并提供了推导出唯一且有意义解所需的所有信息。我们将着手进行分析。\n\n该问题要求比较两种热性能模型：一个是由温度系数 $Q_{10}$ 表征的简单指数关系模型，另一个是更复杂的单峰经验函数 $V(T)$。我们必须计算这两种模型在特定温度区间内预测值之间的相对差异。\n\n首先，我们根据 $Q_{10}$ 的值确定冲刺速度的预测倍数变化。系数 $Q_{10}$ 定义为温度每升高 $10\\,^{\\circ}\\mathrm{C}$ 时生理速率变化的因子。这意味着速率（我们将其表示为 $R(T)$）与温度 $T$ 之間存在指数关系。我们可以将此关系建模为 $R(T) = R_{0} \\cdot k^{T}$，其中 $R_{0}$ 和 $k$ 是常数。根据 $Q_{10}$ 的定义：\n$$\nQ_{10} = \\frac{R(T+10)}{R(T)} = \\frac{R_{0} \\cdot k^{T+10}}{R_{0} \\cdot k^{T}} = k^{10}\n$$\n这给出 $k = (Q_{10})^{1/10}$。因此，速率函数为 $R(T) = R_{0} \\cdot (Q_{10})^{T/10}$。从初始温度 $T_{1}$ 到最终温度 $T_{2}$ 的速率倍数变化是比值 $\\frac{R(T_{2})}{R(T_{1})}$。\n$$\n\\text{Prediction}_{Q_{10}} = \\frac{R(T_{2})}{R(T_{1})} = \\frac{R_{0} \\cdot (Q_{10})^{T_{2}/10}}{R_{0} \\cdot (Q_{10})^{T_{1}/10}} = (Q_{10})^{\\frac{T_{2}-T_{1}}{10}}\n$$\n给定 $Q_{10} = 2.0$，$T_{1} = 22\\,^{\\circ}\\mathrm{C}$ 和 $T_{2} = 29\\,^{\\circ}\\mathrm{C}$。温度区间为 $\\Delta T = T_{2} - T_{1} = 29 - 22 = 7\\,^{\\circ}\\mathrm{C}$。\n代入这些值，预测的倍数变化是：\n$$\n\\text{Prediction}_{Q_{10}} = (2.0)^{\\frac{7}{10}} = 2.0^{0.7}\n$$\n\n接下来，我们使用所提供的冲刺速度函数 $V(T)$ 来计算经验倍数变化。该函数给出如下：\n$$\nV(T) \\;=\\; V_{\\max}\\,\\exp\\!\\left(-\\frac{(T - T_{\\mathrm{opt}})^{2}}{2\\sigma^{2}}\\right)\n$$\n经验倍数变化是比值 $\\frac{V(T_{2})}{V(T_{1})}$。\n$$\n\\frac{V(T_{2})}{V(T_{1})} = \\frac{V_{\\max}\\,\\exp\\!\\left(-\\frac{(T_{2} - T_{\\mathrm{opt}})^{2}}{2\\sigma^{2}}\\right)}{V_{\\max}\\,\\exp\\!\\left(-\\frac{(T_{1} - T_{\\mathrm{opt}})^{2}}{2\\sigma^{2}}\\right)} = \\exp\\left( -\\frac{(T_{2} - T_{\\mathrm{opt}})^{2}}{2\\sigma^{2}} + \\frac{(T_{1} - T_{\\mathrm{opt}})^{2}}{2\\sigma^{2}} \\right)\n$$\n$$\n\\frac{V(T_{2})}{V(T_{1})} = \\exp\\left( \\frac{(T_{1} - T_{\\mathrm{opt}})^{2} - (T_{2} - T_{\\mathrm{opt}})^{2}}{2\\sigma^{2}} \\right)\n$$\n给定参数 $T_{\\mathrm{opt}} = 34\\,^{\\circ}\\mathrm{C}$ 和 $\\sigma = 10\\,^{\\circ}\\mathrm{C}$。温度为 $T_{1} = 22\\,^{\\circ}\\mathrm{C}$ 和 $T_{2} = 29\\,^{\\circ}\\mathrm{C}$。\n我们计算指数中的各项：\n$T_{1} - T_{\\mathrm{opt}} = 22 - 34 = -12\\,^{\\circ}\\mathrm{C}$\n$T_{2} - T_{\\mathrm{opt}} = 29 - 34 = -5\\,^{\\circ}\\mathrm{C}$\n$(T_{1} - T_{\\mathrm{opt}})^{2} = (-12)^{2} = 144\\,(^{\\circ}\\mathrm{C})^{2}$\n$(T_{2} - T_{\\mathrm{opt}})^{2} = (-5)^{2} = 25\\,(^{\\circ}\\mathrm{C})^{2}$\n$2\\sigma^{2} = 2 \\cdot (10)^{2} = 200\\,(^{\\circ}\\mathrm{C})^{2}$\n\n将这些代入比值的表达式中：\n$$\n\\frac{V(T_{2})}{V(T_{1})} = \\exp\\left( \\frac{144 - 25}{200} \\right) = \\exp\\left( \\frac{119}{200} \\right) = \\exp(0.595)\n$$\n\n最后，我们使用提供的公式计算相对差异 $E$：\n$$\nE = \\frac{\\displaystyle \\frac{V(T_{2})}{V(T_{1})} \\;-\\; \\left(\\text{Prediction}_{Q_{10}}\\right)}{\\left(\\text{Prediction}_{Q_{10}}\\right)}\n$$\n代入推导出的表达式：\n$$\nE = \\frac{\\exp(0.595) - 2.0^{0.7}}{2.0^{0.7}}\n$$\n现在我们计算数值。\n$\\text{Prediction}_{Q_{10}} = 2.0^{0.7} \\approx 1.62450479$\n$\\frac{V(T_{2})}{V(T_{1})} = \\exp(0.595) \\approx 1.81303354$\n$$\nE \\approx \\frac{1.81303354 - 1.62450479}{1.62450479} \\approx \\frac{0.18852875}{1.62450479} \\approx 0.11605303\n$$\n问题要求结果四舍五入到4位有效数字。\n$$\nE \\approx 0.1161\n$$\n该值表示在指定的温度范围内，较简单的 $Q_{10}$ 模型相对于经验高斯性能曲线的分数误差。正值表明，在性能曲线的这一部分上，实际性能的增长超过了 $Q_{10}$ 模型的预测，这是预料之中的，因为该动物正在接近其最适温度 $T_{\\mathrm{opt}}$。", "answer": "$$\n\\boxed{0.1161}\n$$", "id": "2619112"}]}